light-on/src/pwm_gen.v
module pwm_gen#(
	parameter DFLT_DUTY = 8'h7F  // Default duty cycle (50%)
)(
	input clk,
	input rst_n,
	input [7:0] duty,  // Duty cycle (0-255)
	output reg pwm_o
);

// Initialize registers
initial begin
	cnt <= 8'b0;
	pwm_o <= DFLT_DUTY;
end

// Counter for generating PWM signal
reg [7:0] cnt;
always @(posedge clk or negedge rst_n) begin
	if(!rst_n)
		cnt <= 1'b0;  // Reset clock counter
	else
		cnt <= cnt + 1'b1;  // Increment clock counter
end

// Update PWM output based on duty cycle and counter
always @(posedge clk or negedge rst_n) begin
	if (!rst_n)
		pwm_o <= DFLT_DUTY;  // Reset to default duty cycle
	else
		pwm_o <= (duty > cnt) ? 1'b1 : 1'b0;  // Simple threshold for PWM output
end
	
endmodule

light-on/src/sec_cnt.v
module sec_cnt #(
    parameter CLOCK_FREQUENCY = 27_000_000,
    parameter A_MINUTE_SEC = 6'd60
)(
    input clk,
    input rst_n,
    output reg [5:0] bin_sec
);

// Generate a tick every 1 second and count seconds from 0 to 59.
wire t1s;
reg [24:0] cnt_1s;

assign t1s = (cnt_1s == CLOCK_FREQUENCY - 1) ? 1'b1 : 1'b0;

initial begin
    cnt_1s = 25'b0;
    bin_sec = 6'b0;
end

// Counter for generating 1-second tick
always @(posedge clk or negedge rst_n) begin
    if (!rst_n)
        cnt_1s <= 25'b0;
        
    else if (cnt_1s < CLOCK_FREQUENCY - 1)
        cnt_1s <= cnt_1s + 1'b1;
    else
        cnt_1s <= 25'b0;
end

// Counter for seconds, resets after reaching A_MINUTE_SEC
always @(posedge clk or negedge rst_n) begin
    if (!rst_n)
        bin_sec <= 6'b0;

    else if (t1s) begin
        if (bin_sec < A_MINUTE_SEC - 6'd1)
            bin_sec <= bin_sec + 6'd1;
        else
            bin_sec <= 6'd0;
    end
    else
        bin_sec <= bin_sec;
end

endmodule

light-on/src/debouncer.v
module debouncer #(
    parameter CLOCK_FREQUENCY = 27_000_000,
    parameter STABLE_TIMES = 20
)(
    input clk,
    input rst_n,
    input key_i,
    output reg key_o
);

// Number of clock cycles for stable time (20ms)
localparam DEBOUNCER_COUNT = CLOCK_FREQUENCY / 1000 * STABLE_TIMES; 

// Initial values for registers
initial begin
    key_tmp = 1'b1;
    key_o = 1'b1;
    cnt = 0;
end

// Debouncing logic: sample the key input every 20ms and update the output if stable
reg key_tmp;
reg [19:0] cnt;
    
always @(posedge clk or negedge rst_n) begin
    if(!rst_n) begin
        // Reset the counter and output states
        cnt <= 0;
        key_tmp <= 1'b1;
        key_o <= 1'b1;
    end
    else begin
        // Increment the counter until it reaches the debouncer count
        if(cnt < DEBOUNCER_COUNT) begin
            cnt <= cnt + 1;
        end
        else begin
            key_tmp <= key_i;
            key_o <= key_tmp;
            cnt <= 0;
        end
    end
end
    
endmodule

light-on/src/key_ctrl.v
module key_ctrl (
    input clk,
    input rst_n,
    input key_i,
    output reg [1:0] key_state
);

localparam S1 = 2'b00;
localparam S2 = 2'b01;
localparam S3 = 2'b10;
localparam S4 = 2'b11;

wire key_o;
debouncer debouncer_inst(
    .clk    (clk),
    .rst_n  (rst_n),
    .key_i  (key_i),
    .key_o  (key_o)
);

reg key_tmp;
always @(posedge clk or negedge rst_n) begin
    if(!rst_n) begin
        key_tmp <= 1'b0; // Reset key_tmp on reset
    end
    else begin
        key_tmp <= key_o;
    end
end

reg [1:0] current_state;
reg [1:0] next_state;
always @(posedge clk or negedge rst_n) begin
    if(!rst_n)
        current_state <= S1; // Reset state
    else
        current_state <= next_state; // Update state on clock edge
end

always @(*) begin
    next_state = current_state; // Default to current state

    if(key_tmp && !key_o) begin // Detect falling edge of key_o
        case (current_state)
            S1: next_state = S2;
            S2: next_state = S3;
            S3: next_state = S4;
            S4: next_state = S1;
            default: next_state = S1; // Default to initial state
        endcase
    end
end

always @(*) begin
    key_state = current_state;
end

endmodule

light-on/src/led.v
module led #(
    // Parameters for clock frequency and brightness control
    parameter CLOCK_FREQUENCY = 27_000_000,  // 27MHz clock
    parameter A_MINUTE_SEC = 6'd60,  // Maximum value for seconds
    parameter BRIGHTNESS = 8'h01  // Maximum brightness (0-255)
)(
    input clk,
    input rst_n,
    input key_i,
    output [5:0] led
);


// Initial values for registers
initial begin
    led_r = 6'b0;
    brightness = BRIGHTNESS;
end

localparam LED_COUNT = 6; // Number of LEDs


reg [7:0] brightness;
wire [1:0] key_state;
key_ctrl key_ctrl_inst (
    .clk       (clk),
    .rst_n     (rst_n_key),
    .key_i     (key_i),
    .key_state (key_state)
);
always @(posedge clk or negedge rst_n_key) begin
    if(!rst_n_key) begin
        brightness <= BRIGHTNESS; // Reset brightness to default
    end
    else begin
        case (key_state)
            2'b00: 
                brightness <= 2'b1;
            default: 
                // Update brightness based on key state (simple mapping for demonstration)
                brightness <= {key_state, key_state, key_state, key_state};
        endcase
    end
end


// Instantiate the second counter to keep track of seconds
wire [5:0] bin_sec;
sec_cnt #(
    .CLOCK_FREQUENCY (CLOCK_FREQUENCY),
    .A_MINUTE_SEC    (A_MINUTE_SEC)
) sec_cnt_inst(
    .clk     (clk),
    .rst_n   (rst_n_key),
    .bin_sec (bin_sec)
);

// Use the binary second register to control the LEDs with PWM for brightness control
wire pwm_signal;
pwm_gen pwm(
    .clk    (clk),
    .rst_n  (rst_n_key),
    .duty   (brightness),
    .pwm_o  (pwm_signal)
);

integer i;
reg[5:0] led_r;
always @(posedge clk or negedge rst_n_key) begin
    if(!rst_n_key) begin
        led_r <= 6'b0;
    end
    else begin
        for(i = 0; i < LED_COUNT; i = i + 1) begin
            led_r[i] <= bin_sec[i] && pwm_signal;
        end
    end
end

// Output the LED states (active low)
assign led = ~led_r;

// Generate a reset signal for the key controller and other modules
wire rst_n_key;
assign rst_n_key = ~rst_n;

endmodule

light-on/tb/led_tb.v
`timescale 1ns/1ps

module led_tb;

reg clk;
reg rst_n;
reg key_i;
wire [5:0] led;

led #(
    .CLOCK_FREQUENCY(8),
    .A_MINUTE_SEC(6'd4),
    .BRIGHTNESS(8'h40)
) uut (
    .clk   (clk),
    .rst_n (rst_n),
    .key_i (key_i),
    .led   (led)
);

defparam uut.key_ctrl_inst.debouncer_inst.CLOCK_FREQUENCY = 1000;
defparam uut.key_ctrl_inst.debouncer_inst.STABLE_TIMES = 1;

always #5 clk = ~clk;

task automatic press_key;
begin
    key_i = 1'b0;
    repeat (6) @(posedge clk);
    key_i = 1'b1;
    repeat (6) @(posedge clk);
end
endtask

initial begin
    clk = 1'b0;
    rst_n = 1'b1;
    key_i = 1'b1;

    $dumpfile("tb/led_tb.vcd");
    $dumpvars(0, led_tb);

    repeat (4) @(posedge clk);
    rst_n = 1'b0;

    repeat (12) @(posedge clk);
    press_key();
    press_key();
    press_key();

    repeat (24) @(posedge clk);
    $finish;
end

initial begin
    $display("time\trst_n\trst_n_key\tkey_i\tkey_state\tbin_sec\tbrightness\tpwm\tled");
    $monitor("%0t\t%b\t%b\t%b\t%02b\t%02d\t0x%0h\t%b\t%06b",
        $time,
        rst_n,
        uut.rst_n_key,
        key_i,
        uut.key_state,
        uut.bin_sec,
        uut.brightness,
        uut.pwm_signal,
        led
    );
end

endmodule

light-on/tb/led_tb.vcd
$date
	Sat Apr 04 06:41:10 2026
$end
$version
	Icarus Verilog
$end
$timescale
	1ps
$end
$scope module led_tb $end
$var wire 6 ! led [5:0] $end
$var reg 1 " clk $end
$var reg 1 # key_i $end
$var reg 1 $ rst_n $end
$scope module uut $end
$var wire 1 " clk $end
$var wire 1 # key_i $end
$var wire 6 % led [5:0] $end
$var wire 1 $ rst_n $end
$var wire 1 & rst_n_key $end
$var wire 1 ' pwm_signal $end
$var wire 2 ( key_state [1:0] $end
$var wire 6 ) bin_sec [5:0] $end
$var parameter 6 * A_MINUTE_SEC $end
$var parameter 8 + BRIGHTNESS $end
$var parameter 32 , CLOCK_FREQUENCY $end
$var parameter 32 - LED_COUNT $end
$var reg 8 . brightness [7:0] $end
$var reg 6 / led_r [5:0] $end
$var integer 32 0 i [31:0] $end
$scope module key_ctrl_inst $end
$var wire 1 " clk $end
$var wire 1 # key_i $end
$var wire 1 & rst_n $end
$var wire 1 1 key_o $end
$var parameter 2 2 S1 $end
$var parameter 2 3 S2 $end
$var parameter 2 4 S3 $end
$var parameter 2 5 S4 $end
$var reg 2 6 current_state [1:0] $end
$var reg 2 7 key_state [1:0] $end
$var reg 1 8 key_tmp $end
$var reg 2 9 next_state [1:0] $end
$scope module debouncer_inst $end
$var wire 1 " clk $end
$var wire 1 # key_i $end
$var wire 1 & rst_n $end
$var parameter 32 : CLOCK_FREQUENCY $end
$var parameter 64 ; DEBOUNCER_COUNT $end
$var parameter 32 < STABLE_TIMES $end
$var reg 20 = cnt [19:0] $end
$var reg 1 1 key_o $end
$var reg 1 > key_tmp $end
$upscope $end
$upscope $end
$scope module pwm $end
$var wire 1 " clk $end
$var wire 8 ? duty [7:0] $end
$var wire 1 & rst_n $end
$var parameter 8 @ DFLT_DUTY $end
$var reg 8 A cnt [7:0] $end
$var reg 1 ' pwm_o $end
$upscope $end
$scope module sec_cnt_inst $end
$var wire 1 " clk $end
$var wire 1 & rst_n $end
$var wire 1 B t1s $end
$var parameter 6 C A_MINUTE_SEC $end
$var parameter 32 D CLOCK_FREQUENCY $end
$var reg 6 E bin_sec [5:0] $end
$var reg 25 F cnt_1s [24:0] $end
$upscope $end
$upscope $end
$scope task press_key $end
$upscope $end
$upscope $end
$enddefinitions $end
$comment Show the parameter values. $end
$dumpall
b1000 D
b100 C
b1111111 @
b1 <
b1 ;
b1111101000 :
b11 5
b10 4
b1 3
b0 2
b110 -
b1000 ,
b1000000 +
b100 *
$end
#0
$dumpvars
b0 F
b0 E
0B
b0 A
b1000000 ?
1>
b0 =
b0 9
08
b0 7
b0 6
11
bx 0
b0 /
b1000000 .
b0 )
b0 (
1'
0&
b111111 %
1$
1#
0"
b111111 !
$end
#5000
1"
#10000
0"
#15000
1"
#20000
0"
#25000
1"
#30000
0"
#35000
1&
0$
1"
#40000
0"
#45000
b1 .
b1 ?
b1 A
b1 F
18
b1 =
b110 0
1"
#50000
0"
#55000
b0 =
b10 F
b10 A
0'
b110 0
1"
#60000
0"
#65000
b11 A
b11 F
b1 =
b110 0
1"
#70000
0"
#75000
b0 =
b100 F
b100 A
b110 0
1"
#80000
0"
#85000
b101 A
b101 F
b1 =
b110 0
1"
#90000
0"
#95000
b0 =
b110 F
b110 A
b110 0
1"
#100000
0"
#105000
1B
b111 A
b111 F
b1 =
b110 0
1"
#110000
0"
#115000
0B
b0 =
b0 F
b1 )
b1 E
b1000 A
b110 0
1"
#120000
0"
#125000
b1001 A
b1 F
b1 =
b110 0
1"
#130000
0"
#135000
b0 =
b10 F
b1010 A
b110 0
1"
#140000
0"
#145000
b1011 A
b11 F
b1 =
b110 0
1"
#150000
0"
#155000
b0 =
0>
b100 F
b1100 A
b110 0
0#
1"
#160000
0"
#165000
b1101 A
b101 F
b1 =
b110 0
1"
#170000
0"
#175000
b1 9
b0 =
01
b110 F
b1110 A
b110 0
1"
#180000
0"
#185000
1B
b1 (
b1 7
b1111 A
b111 F
b1 6
08
b1 =
b110 0
1"
#190000
0"
#195000
0B
b0 =
b0 F
b10 )
b10 E
b10000 A
b1010101 .
b1010101 ?
b110 0
1"
#200000
0"
#205000
1'
b10001 A
b1 F
b1 =
b110 0
1"
#210000
0"
#215000
b111101 !
b111101 %
b0 =
1>
b10 F
b10010 A
b10 /
b110 0
1#
1"
#220000
0"
#225000
b10011 A
b11 F
b1 =
b110 0
1"
#230000
0"
#235000
b0 =
11
b100 F
b10100 A
b110 0
1"
#240000
0"
#245000
b10101 A
b101 F
18
b1 =
b110 0
1"
#250000
0"
#255000
b0 =
b110 F
b10110 A
b110 0
1"
#260000
0"
#265000
1B
b10111 A
b111 F
b1 =
b110 0
1"
#270000
0"
#275000
0B
b0 =
0>
b0 F
b11 )
b11 E
b11000 A
b110 0
0#
1"
#280000
0"
#285000
b111100 !
b111100 %
b11 /
b11001 A
b1 F
b1 =
b110 0
1"
#290000
0"
#295000
b10 9
b0 =
01
b10 F
b11010 A
b110 0
1"
#300000
0"
#305000
b10 (
b10 7
b11011 A
b11 F
b10 6
08
b1 =
b110 0
1"
#310000
0"
#315000
b0 =
b100 F
b11100 A
b10101010 .
b10101010 ?
b110 0
1"
#320000
0"
#325000
b11101 A
b101 F
b1 =
b110 0
1"
#330000
0"
#335000
b0 =
1>
b110 F
b11110 A
b110 0
1#
1"
#340000
0"
#345000
1B
b11111 A
b111 F
b1 =
b110 0
1"
#350000
0"
#355000
0B
b0 =
11
b0 F
b0 )
b0 E
b100000 A
b110 0
1"
#360000
0"
#365000
b111111 !
b111111 %
b0 /
b100001 A
b1 F
18
b1 =
b110 0
1"
#370000
0"
#375000
b0 =
b10 F
b100010 A
b110 0
1"
#380000
0"
#385000
b100011 A
b11 F
b1 =
b110 0
1"
#390000
0"
#395000
b0 =
0>
b100 F
b100100 A
b110 0
0#
1"
#400000
0"
#405000
b100101 A
b101 F
b1 =
b110 0
1"
#410000
0"
#415000
b11 9
b0 =
01
b110 F
b100110 A
b110 0
1"
#420000
0"
#425000
1B
b11 (
b11 7
b100111 A
b111 F
b11 6
08
b1 =
b110 0
1"
#430000
0"
#435000
0B
b0 =
b0 F
b1 )
b1 E
b101000 A
b11111111 .
b11111111 ?
b110 0
1"
#440000
0"
#445000
b111110 !
b111110 %
b1 /
b101001 A
b1 F
b1 =
b110 0
1"
#450000
0"
#455000
b0 =
1>
b10 F
b101010 A
b110 0
1#
1"
#460000
0"
#465000
b101011 A
b11 F
b1 =
b110 0
1"
#470000
0"
#475000
b0 =
11
b100 F
b101100 A
b110 0
1"
#480000
0"
#485000
b101101 A
b101 F
18
b1 =
b110 0
1"
#490000
0"
#495000
b0 =
b110 F
b101110 A
b110 0
1"
#500000
0"
#505000
1B
b101111 A
b111 F
b1 =
b110 0
1"
#510000
0"
#515000
0B
b0 =
b0 F
b10 )
b10 E
b110000 A
b110 0
1"
#520000
0"
#525000
b111101 !
b111101 %
b10 /
b110001 A
b1 F
b1 =
b110 0
1"
#530000
0"
#535000
b0 =
b10 F
b110010 A
b110 0
1"
#540000
0"
#545000
b110011 A
b11 F
b1 =
b110 0
1"
#550000
0"
#555000
b0 =
b100 F
b110100 A
b110 0
1"
#560000
0"
#565000
b110101 A
b101 F
b1 =
b110 0
1"
#570000
0"
#575000
b0 =
b110 F
b110110 A
b110 0
1"
#580000
0"
#585000
1B
b110111 A
b111 F
b1 =
b110 0
1"
#590000
0"
#595000
0B
b0 =
b0 F
b11 )
b11 E
b111000 A
b110 0
1"
#600000
0"
#605000
b111100 !
b111100 %
b11 /
b111001 A
b1 F
b1 =
b110 0
1"
#610000
0"
#615000
b0 =
b10 F
b111010 A
b110 0
1"
#620000
0"
#625000
b111011 A
b11 F
b1 =
b110 0
1"
#630000
0"
#635000
b0 =
b100 F
b111100 A
b110 0
1"
#640000
0"
#645000
b111101 A
b101 F
b1 =
b110 0
1"
#650000
0"
#655000
b0 =
b110 F
b111110 A
b110 0
1"
#660000
0"
#665000
1B
b111111 A
b111 F
b1 =
b110 0
1"
#670000
0"
#675000
0B
b0 =
b0 F
b0 )
b0 E
b1000000 A
b110 0
1"
#680000
0"
#685000
b111111 !
b111111 %
b0 /
b1000001 A
b1 F
b1 =
b110 0
1"
#690000
0"
#695000
b0 =
b10 F
b1000010 A
b110 0
1"
#700000
0"
#705000
b1000011 A
b11 F
b1 =
b110 0
1"
#710000
0"
#715000
b0 =
b100 F
b1000100 A
b110 0
1"
#720000
0"
#725000
b1000101 A
b101 F
b1 =
b110 0
1"
#730000
0"
#735000
b0 =
b110 F
b1000110 A
b110 0
1"
#740000
0"
#745000
1B
b1000111 A
b111 F
b1 =
b110 0
1"
#750000
0"
#755000
0B
b0 =
b0 F
b1 )
b1 E
b1001000 A
b110 0
1"
