hdmi_base/src/pattern_gen.v
module pattern_gen # (
    parameter H_ACTIVE = 1280,
    parameter V_ACTIVE = 720
) (
    input wire clk_hdmi,
    input wire rst_n,

    input wire [11:0] x,
    input wire [11:0] y,
    input wire de,
    input wire frame_end,

    output reg [23:0] rgb_o
);

// Generate a simple color pattern based on the pixel position and frame count
reg [23:0] frame_cnt;
always @(posedge clk_hdmi or negedge rst_n) begin
    if (!rst_n)
        frame_cnt <= 24'd0;
    else if (frame_end)
        frame_cnt <= frame_cnt + 24'd1;
end

// Update RGB output based on the current pixel position and frame count
always @(posedge clk_hdmi or negedge rst_n) begin
    if (!rst_n)
        rgb_o <= 24'h000000;
    else if (!de)
        rgb_o <= 24'h000000;
    else begin
        // Create a simple color pattern that changes every frame and varies across the screen
        // One example: Use the upper bits of x to create vertical color bands, and frame count to animate
        // Test for 720p: 1280x720, so x[9:7] gives us 8 vertical bands (1280/8 = 160 pixels per band)
        case (x[9:7])
            3'b000: rgb_o <= 24'hFF0000 ^ {frame_cnt[7:0], 16'h0000};
            3'b001: rgb_o <= 24'h00FF00 ^ {8'h00, frame_cnt[7:0], 8'h00};
            3'b010: rgb_o <= 24'h0000FF ^ {16'h0000, frame_cnt[7:0]};
            3'b011: rgb_o <= 24'h00FFFF ^ {frame_cnt[7:0], 8'h00, 8'h00};
            3'b100: rgb_o <= 24'hFF00FF ^ {8'h00, frame_cnt[7:0], 8'h00};
            3'b101: rgb_o <= 24'hFFFF00 ^ {16'h0000, frame_cnt[7:0]};
            default: rgb_o <= {x[7:0], y[7:0], frame_cnt[7:0]};
        endcase
    end
end 
endmodule

hdmi_base/tb/pattern_gen_tb.v
`timescale 1ns/1ps

module pattern_gen_tb;

reg clk_hdmi;
reg rst_n;
reg [11:0] x;
reg [11:0] y;
reg de;
reg frame_end;
wire [23:0] rgb_o;

integer frame_index;

pattern_gen #(
    .H_ACTIVE(16),
    .V_ACTIVE(8)
) uut (
    .clk_hdmi(clk_hdmi),
    .rst_n(rst_n),
    .x(x),
    .y(y),
    .de(de),
    .frame_end(frame_end),
    .rgb_o(rgb_o)
);

always #5 clk_hdmi = ~clk_hdmi;

task automatic drive_pixel;
    input [11:0] pixel_x;
    input [11:0] pixel_y;
    input pixel_de;
    input pixel_frame_end;
begin
    x = pixel_x;
    y = pixel_y;
    de = pixel_de;
    frame_end = pixel_frame_end;
    @(posedge clk_hdmi);
end
endtask

initial begin
    clk_hdmi = 1'b0;
    rst_n = 1'b0;
    x = 12'd0;
    y = 12'd0;
    de = 1'b0;
    frame_end = 1'b0;
    frame_index = 0;

    $dumpfile("tb/pattern_gen_tb.vcd");
    $dumpvars(0, pattern_gen_tb);

    repeat (4) @(posedge clk_hdmi);
    rst_n = 1'b1;

    for (frame_index = 0; frame_index < 3; frame_index = frame_index + 1) begin
        drive_pixel(12'd0, 12'd0, 1'b0, 1'b0);
        drive_pixel(12'd0, 12'd0, 1'b1, 1'b0);
        drive_pixel(12'd160, 12'd0, 1'b1, 1'b0);
        drive_pixel(12'd320, 12'd0, 1'b1, 1'b0);
        drive_pixel(12'd480, 12'd0, 1'b1, 1'b0);
        drive_pixel(12'd640, 12'd0, 1'b1, 1'b0);
        drive_pixel(12'd800, 12'd0, 1'b1, 1'b0);
        drive_pixel(12'd1120, 12'd64, 1'b1, 1'b0);
        drive_pixel(12'd1279, 12'd719, 1'b1, 1'b1);
        drive_pixel(12'd0, 12'd0, 1'b0, 1'b0);
    end

    repeat (4) @(posedge clk_hdmi);
    $finish;
end

always @(posedge clk_hdmi) begin
    if (!rst_n && rgb_o !== 24'h000000) begin
        $display("ERROR: rgb_o not cleared during reset at time=%0t rgb=%h", $time, rgb_o);
        $finish;
    end

    if (rst_n && !de && rgb_o !== 24'h000000) begin
        $display("ERROR: rgb_o not blanked when de=0 at time=%0t rgb=%h", $time, rgb_o);
        $finish;
    end

    if (rst_n && de) begin
        $display("time=%0t frame_cnt=%0d x=%0d y=%0d rgb=%h", $time, uut.frame_cnt, x, y, rgb_o);
    end
end

endmodule

hdmi_base/tb/pattern_gen_tb.vcd
$date
	Mon Apr 06 20:48:33 2026
$end
$version
	Icarus Verilog
$end
$timescale
	1ps
$end
$scope module pattern_gen_tb $end
$var wire 24 ! rgb_o [23:0] $end
$var reg 1 " clk_hdmi $end
$var reg 1 # de $end
$var reg 1 $ frame_end $end
$var reg 1 % rst_n $end
$var reg 12 & x [11:0] $end
$var reg 12 ' y [11:0] $end
$var integer 32 ( frame_index [31:0] $end
$scope module uut $end
$var wire 1 " clk_hdmi $end
$var wire 1 # de $end
$var wire 1 $ frame_end $end
$var wire 1 % rst_n $end
$var wire 12 ) x [11:0] $end
$var wire 12 * y [11:0] $end
$var parameter 32 + H_ACTIVE $end
$var parameter 32 , V_ACTIVE $end
$var reg 24 - frame_cnt [23:0] $end
$var reg 24 . rgb_o [23:0] $end
$upscope $end
$scope task drive_pixel $end
$upscope $end
$upscope $end
$enddefinitions $end
$comment Show the parameter values. $end
$dumpall
b1000 ,
b10000 +
$end
#0
$dumpvars
b0 .
b0 -
b0 *
b0 )
b0 (
b0 '
b0 &
0%
0$
0#
0"
b0 !
$end
#5000
1"
#10000
0"
#15000
1"
#20000
0"
#25000
1"
#30000
0"
#35000
1%
1"
#40000
0"
#45000
b111111110000000000000000 !
b111111110000000000000000 .
1#
1"
#50000
0"
#55000
b1111111100000000 !
b1111111100000000 .
b10100000 &
b10100000 )
1"
#60000
0"
#65000
b11111111 !
b11111111 .
b101000000 &
b101000000 )
1"
#70000
0"
#75000
b1111111111111111 !
b1111111111111111 .
b111100000 &
b111100000 )
1"
#80000
0"
#85000
b111111111111111100000000 !
b111111111111111100000000 .
b1010000000 &
b1010000000 )
1"
#90000
0"
#95000
b1000000000000000000000 !
b1000000000000000000000 .
b1100100000 &
b1100100000 )
1"
#100000
0"
#105000
b111111110000000000000000 !
b111111110000000000000000 .
b1000000 '
b1000000 *
b10001100000 &
b10001100000 )
1"
#110000
0"
#115000
b1 -
b1111111100000000 !
b1111111100000000 .
1$
b1011001111 '
b1011001111 *
b10011111111 &
b10011111111 )
1"
#120000
0"
#125000
b0 !
b0 .
0$
0#
b0 '
b0 *
b0 &
b0 )
1"
#130000
0"
#135000
b1 (
1"
#140000
0"
#145000
b111111100000000000000000 !
b111111100000000000000000 .
1#
1"
#150000
0"
#155000
b1111111000000000 !
b1111111000000000 .
b10100000 &
b10100000 )
1"
#160000
0"
#165000
b11111110 !
b11111110 .
b101000000 &
b101000000 )
1"
#170000
0"
#175000
b11111111111111111 !
b11111111111111111 .
b111100000 &
b111100000 )
1"
#180000
0"
#185000
b111111111111111100000001 !
b111111111111111100000001 .
b1010000000 &
b1010000000 )
1"
#190000
0"
#195000
b1000000000000000000001 !
b1000000000000000000001 .
b1100100000 &
b1100100000 )
1"
#200000
0"
#205000
b111111100000000000000000 !
b111111100000000000000000 .
b1000000 '
b1000000 *
b10001100000 &
b10001100000 )
1"
#210000
0"
#215000
b10 -
b1111111000000000 !
b1111111000000000 .
1$
b1011001111 '
b1011001111 *
b10011111111 &
b10011111111 )
1"
#220000
0"
#225000
b0 !
b0 .
0$
0#
b0 '
b0 *
b0 &
b0 )
1"
#230000
0"
#235000
b10 (
1"
#240000
0"
#245000
b111111010000000000000000 !
b111111010000000000000000 .
1#
1"
#250000
0"
#255000
b1111110100000000 !
b1111110100000000 .
b10100000 &
b10100000 )
1"
#260000
0"
#265000
b11111101 !
b11111101 .
b101000000 &
b101000000 )
1"
#270000
0"
#275000
b101111111111111111 !
b101111111111111111 .
b111100000 &
b111100000 )
1"
#280000
0"
#285000
b111111111111111100000010 !
b111111111111111100000010 .
b1010000000 &
b1010000000 )
1"
#290000
0"
#295000
b1000000000000000000010 !
b1000000000000000000010 .
b1100100000 &
b1100100000 )
1"
#300000
0"
#305000
b111111010000000000000000 !
b111111010000000000000000 .
b1000000 '
b1000000 *
b10001100000 &
b10001100000 )
1"
#310000
0"
#315000
b11 -
b1111110100000000 !
b1111110100000000 .
1$
b1011001111 '
b1011001111 *
b10011111111 &
b10011111111 )
1"
#320000
0"
#325000
b0 !
b0 .
0$
0#
b0 '
b0 *
b0 &
b0 )
1"
#330000
0"
#335000
b11 (
1"
