hdmi_base/src/tmds_encoder.v
module tmds_encoder (
    input clk_hdmi,
    input rst_n,

    input de,            // Data Enable signal indicating active video data
    input wire [7:0] data_i,  // 8-bit input data for encoding
    input [1:0] ctrl_i,  // Control signals for blanking intervals

    output reg [9:0] tmds_o
);

// TMDS encoding: 10-bit output based on input data and control signals
wire [3:0] ones_count =
    data_i[0] + data_i[1] + data_i[2] + data_i[3] + 
    data_i[4] + data_i[5] + data_i[6] + data_i[7];

wire use_xnor;
assign use_xnor = (ones_count > 4) || ((ones_count == 4) && (data_i[0] == 1'b0));

wire [8:0] q_m_next;
assign q_m_next[0] = data_i[0];
assign q_m_next[1] = use_xnor ? ~(q_m_next[0] ^ data_i[1]) : (q_m_next[0] ^ data_i[1]);
assign q_m_next[2] = use_xnor ? ~(q_m_next[1] ^ data_i[2]) : (q_m_next[1] ^ data_i[2]);
assign q_m_next[3] = use_xnor ? ~(q_m_next[2] ^ data_i[3]) : (q_m_next[2] ^ data_i[3]);
assign q_m_next[4] = use_xnor ? ~(q_m_next[3] ^ data_i[4]) : (q_m_next[3] ^ data_i[4]);
assign q_m_next[5] = use_xnor ? ~(q_m_next[4] ^ data_i[5]) : (q_m_next[4] ^ data_i[5]);
assign q_m_next[6] = use_xnor ? ~(q_m_next[5] ^ data_i[6]) : (q_m_next[5] ^ data_i[6]);
assign q_m_next[7] = use_xnor ? ~(q_m_next[6] ^ data_i[7]) : (q_m_next[6] ^ data_i[7]);
assign q_m_next[8] = ~use_xnor;

reg [8:0] q_m;
always @(posedge clk_hdmi or negedge rst_n) begin
    if (!rst_n)
        q_m <= 9'b0;
    else if (!de)
        q_m <= 9'b0;
    else
        q_m <= q_m_next;
end


// Control signal encoding for blanking intervals
reg signed [4:0] disparity;
reg [3:0] dc_ones_cnt;
reg dc_invert;
reg [3:0] dc_n1_final;
reg [9:0] tmds_next;

always @(posedge clk_hdmi or negedge rst_n) begin
    if(!rst_n) begin
        tmds_o <= 10'b0;
        disparity <= 5'sd0;
    end
    else begin
        if (!de) begin
            // Output control codes during blanking intervals based on ctrl_i
            case (ctrl_i)
                2'b00: tmds_o <= 10'b1101010100; // Control code for blanking
                2'b01: tmds_o <= 10'b0010101011; // Control code for blanking
                2'b10: tmds_o <= 10'b0101010100; // Control code for blanking
                2'b11: tmds_o <= 10'b1010101011; // Control code for blanking
                default: tmds_o <= 10'b0;
            endcase
            disparity <= 5'sd0;

        end else begin
            // Update disparity based on the number of ones in the encoded data
            dc_ones_cnt = 
                q_m[0] + q_m[1] + q_m[2] + q_m[3] +
                q_m[4] + q_m[5] + q_m[6] + q_m[7];

            // Determine whether to invert the data based on the current disparity and the number of ones
            dc_invert = 
                (disparity == 0 || dc_ones_cnt == 4) ? ~q_m[8] : 
                    (disparity > 0) ? (dc_ones_cnt > 4) : (dc_ones_cnt < 4);

            // Build next TMDS symbol first so disparity uses same-cycle value.
            tmds_next[9] = dc_invert;
            tmds_next[8] = q_m[8];
            tmds_next[7:0] = dc_invert ? ~q_m[7:0] : q_m[7:0];

            tmds_o <= tmds_next;

            // Update disparity counter based on the number of ones in the output
            dc_n1_final = 
                tmds_next[9] + tmds_next[8] + tmds_next[7] + tmds_next[6] +
                tmds_next[5] + tmds_next[4] + tmds_next[3] + tmds_next[2] +
                tmds_next[1] + tmds_next[0];

            disparity <= disparity + 2*dc_n1_final - 10;
        end
    end
end
    
endmodule

hdmi_base/tb/tmds_encoder_tb.v
`timescale 1ns/1ps

module tmds_encoder_tb;

reg clk_hdmi;
reg rst_n;
reg de;
reg [7:0] data_i;
reg [1:0] ctrl_i;
wire [9:0] tmds_o;

integer test_idx;

tmds_encoder uut (
    .clk_hdmi(clk_hdmi),
    .rst_n(rst_n),
    .de(de),
    .data_i(data_i),
    .ctrl_i(ctrl_i),
    .tmds_o(tmds_o)
);

always #5 clk_hdmi = ~clk_hdmi;

task automatic apply_step;
    input step_de;
    input [7:0] step_data;
    input [1:0] step_ctrl;
    input [127:0] step_name;
    begin
        de = step_de;
        data_i = step_data;
        ctrl_i = step_ctrl;

        @(posedge clk_hdmi);
        #1;
        $display("time=%0t step=%0s de=%b data=%h ctrl=%b q_m=%b disparity=%0d tmds=%b",
            $time,
            step_name,
            step_de,
            step_data,
            step_ctrl,
            uut.q_m,
            uut.disparity,
            tmds_o
        );
    end
endtask

task automatic check_ctrl_code;
    input [1:0] ctrl;
    input [9:0] expected;
    begin
        if (tmds_o !== expected) begin
            $display("ERROR: control code mismatch at time=%0t ctrl=%b expected=%b got=%b", $time, ctrl, expected, tmds_o);
            $finish;
        end
    end
endtask

task automatic ensure_known_output;
    begin
        if (^tmds_o === 1'bx) begin
            $display("ERROR: tmds_o has X/Z at time=%0t value=%b", $time, tmds_o);
            $finish;
        end
    end
endtask

initial begin
    clk_hdmi = 1'b0;
    rst_n = 1'b0;
    de = 1'b0;
    data_i = 8'h00;
    ctrl_i = 2'b00;

    $dumpfile("tb/tmds_encoder_tb.vcd");
    $dumpvars(0, tmds_encoder_tb);

    repeat (3) @(posedge clk_hdmi);
    #1;
    if (tmds_o !== 10'b0) begin
        $display("ERROR: reset output mismatch at time=%0t expected=0000000000 got=%b", $time, tmds_o);
        $finish;
    end

    rst_n = 1'b1;

    apply_step(1'b0, 8'h00, 2'b00, "ctrl00");
    ensure_known_output();
    check_ctrl_code(2'b00, 10'b1101010100);

    apply_step(1'b0, 8'h00, 2'b01, "ctrl01");
    ensure_known_output();
    check_ctrl_code(2'b01, 10'b0010101011);

    apply_step(1'b0, 8'h00, 2'b10, "ctrl10");
    ensure_known_output();
    check_ctrl_code(2'b10, 10'b0101010100);

    apply_step(1'b0, 8'h00, 2'b11, "ctrl11");
    ensure_known_output();
    check_ctrl_code(2'b11, 10'b1010101011);

    apply_step(1'b1, 8'h00, 2'b00, "data00");
    ensure_known_output();
    apply_step(1'b1, 8'hff, 2'b00, "dataff");
    ensure_known_output();
    apply_step(1'b1, 8'h55, 2'b00, "data55");
    ensure_known_output();
    apply_step(1'b1, 8'haa, 2'b00, "dataaa");
    ensure_known_output();
    apply_step(1'b1, 8'h0f, 2'b00, "data0f");
    ensure_known_output();
    apply_step(1'b1, 8'hf0, 2'b00, "dataf0");
    ensure_known_output();
    apply_step(1'b1, 8'h81, 2'b00, "data81");
    ensure_known_output();
    apply_step(1'b1, 8'h18, 2'b00, "data18");
    ensure_known_output();

    for (test_idx = 0; test_idx < 8; test_idx = test_idx + 1) begin
        apply_step(1'b1, test_idx * 8'h1d, 2'b00, "sweep");
        ensure_known_output();
    end

    rst_n = 1'b0;
    @(posedge clk_hdmi);
    #1;
    if (tmds_o !== 10'b0) begin
        $display("ERROR: mid-run reset output mismatch at time=%0t got=%b", $time, tmds_o);
        $finish;
    end

    rst_n = 1'b1;
    apply_step(1'b0, 8'h00, 2'b00, "ctrl00_after_reset");
    ensure_known_output();
    check_ctrl_code(2'b00, 10'b1101010100);

    repeat (3) @(posedge clk_hdmi);
    $finish;
end

endmodule

hdmi_base/tb/tmds_encoder_tb.vcd
$date
	Tue Apr 07 04:19:46 2026
$end
$version
	Icarus Verilog
$end
$timescale
	1ps
$end
$scope module tmds_encoder_tb $end
$var wire 10 ! tmds_o [9:0] $end
$var reg 1 " clk_hdmi $end
$var reg 2 # ctrl_i [1:0] $end
$var reg 8 $ data_i [7:0] $end
$var reg 1 % de $end
$var reg 1 & rst_n $end
$var integer 32 ' test_idx [31:0] $end
$scope module uut $end
$var wire 1 " clk_hdmi $end
$var wire 2 ( ctrl_i [1:0] $end
$var wire 8 ) data_i [7:0] $end
$var wire 1 % de $end
$var wire 1 & rst_n $end
$var wire 1 * use_xnor $end
$var wire 9 + q_m_next [8:0] $end
$var wire 4 , ones_count [3:0] $end
$var reg 1 - dc_invert $end
$var reg 4 . dc_n1_final [3:0] $end
$var reg 4 / dc_ones_cnt [3:0] $end
$var reg 5 0 disparity [4:0] $end
$var reg 9 1 q_m [8:0] $end
$var reg 10 2 tmds_next [9:0] $end
$var reg 10 3 tmds_o [9:0] $end
$upscope $end
$scope task apply_step $end
$upscope $end
$scope task check_ctrl_code $end
$upscope $end
$scope task ensure_known_output $end
$upscope $end
$upscope $end
$enddefinitions $end
$comment Show the parameter values. $end
$dumpall
$end
#0
$dumpvars
b0 3
bx 2
b0 1
b0 0
bx /
bx .
x-
b0 ,
b100000000 +
0*
b0 )
b0 (
bx '
0&
0%
b0 $
b0 #
0"
b0 !
$end
#5000
1"
#10000
0"
#15000
1"
#20000
0"
#25000
1"
#26000
1&
#30000
0"
#35000
b1101010100 !
b1101010100 3
1"
#36000
b1 #
b1 (
#40000
0"
#45000
b10101011 !
b10101011 3
1"
#46000
b10 #
b10 (
#50000
0"
#55000
b101010100 !
b101010100 3
1"
#56000
b11 #
b11 (
#60000
0"
#65000
b1010101011 !
b1010101011 3
1"
#66000
b0 #
b0 (
1%
#70000
0"
#75000
b100000000 1
b1000 0
b1011111111 !
b1011111111 3
b1001 .
b1011111111 2
1-
b0 /
1"
#76000
1*
b1000 ,
b11111111 +
b11111111 $
b11111111 )
#80000
0"
#85000
b0 0
b100000000 !
b100000000 3
b11111111 1
b1 .
b100000000 2
0-
1"
#86000
b100110011 +
0*
b100 ,
b1010101 $
b1010101 )
#90000
0"
#95000
b100110011 1
b11000 0
b1000000000 !
b1000000000 3
b1000000000 2
1-
b1000 /
1"
#96000
1*
b100 ,
b11001100 +
b10101010 $
b10101010 )
#100000
0"
#105000
b100110011 !
b100110011 3
b11001100 1
b101 .
b100110011 2
0-
b100 /
1"
#106000
0*
b100 ,
b100000101 +
b1111 $
b1111 )
#110000
0"
#115000
b100000101 1
b1000110011 !
b1000110011 3
b1000110011 2
1-
1"
#116000
1*
b100 ,
b11111010 +
b11110000 $
b11110000 )
#120000
0"
#125000
b11110 0
b1111111010 !
b1111111010 3
b11111010 1
b1000 .
b1111111010 2
b10 /
1"
#126000
0*
b10 ,
b101111111 +
b10000001 $
b10000001 )
#130000
0"
#135000
b101111111 1
b0 0
b11111010 !
b11111010 3
b110 .
b11111010 2
0-
b110 /
1"
#136000
b10 ,
b100001000 +
b11000 $
b11000 )
#140000
0"
#145000
b110 0
b101111111 !
b101111111 3
b100001000 1
b1000 .
b101111111 2
b111 /
1"
#146000
b100000000 +
b0 ,
b0 $
b0 )
b0 '
#150000
0"
#155000
b100000000 1
b0 0
b100001000 !
b100001000 3
b10 .
b100001000 2
b1 /
1"
#156000
b100 ,
b100001011 +
b11101 $
b11101 )
b1 '
#160000
0"
#165000
b11000 0
b100000000 !
b100000000 3
b100001011 1
b1 .
b100000000 2
b0 /
1"
#166000
1*
b100 ,
b10111100 +
b111010 $
b111010 )
b10 '
#170000
0"
#175000
b10111100 1
b11100 0
b1111110100 !
b1111110100 3
b111 .
b1111110100 2
1-
b11 /
1"
#176000
b101 ,
b1100111 +
b1010111 $
b1010111 )
b11 '
#180000
0"
#185000
b10111100 !
b10111100 3
b1100111 1
b101 .
b10111100 2
0-
b101 /
1"
#186000
b100 ,
b10000110 +
b1110100 $
b1110100 )
b100 '
#190000
0"
#195000
b10000110 1
b1100111 !
b1100111 3
b1100111 2
1"
#196000
0*
b11 ,
b110001111 +
b10010001 $
b10010001 )
b101 '
#200000
0"
#205000
b11110 0
b1001111001 !
b1001111001 3
b110001111 1
b110 .
b1001111001 2
1-
b11 /
1"
#206000
1*
b101 ,
b110000 +
b10101110 $
b10101110 )
b110 '
#210000
0"
#215000
b110000 1
b0 0
b110001111 !
b110001111 3
b110001111 2
0-
b101 /
1"
#216000
b101 ,
b10011 +
b11001011 $
b11001011 )
b111 '
#220000
0"
#225000
b100 0
b1011001111 !
b1011001111 3
b10011 1
b111 .
b1011001111 2
1-
b10 /
1"
#226000
b0 1
b0 0
b0 !
b0 3
0&
b1000 '
#230000
0"
#235000
1"
#236000
0*
b0 ,
b100000000 +
b0 $
b0 )
0%
1&
#240000
0"
#245000
b1101010100 !
b1101010100 3
1"
