hdmi_base/src/tmds_encoder.v
module tmds_encoder (
    input clk_hdmi,
    input rst_n,

    input de,            // Data Enable signal indicating active video data
    input wire [7:0] data_i,  // 8-bit input data for encoding
    input [1:0] ctrl_i,  // Control signals for blanking intervals

    output reg [9:0] tmds_o
);

// TMDS encoding: 10-bit output based on input data and control signals
wire [3:0] ones_count =
    data_i[0] + data_i[1] + data_i[2] + data_i[3] + 
    data_i[4] + data_i[5] + data_i[6] + data_i[7];

wire use_xnor;
assign use_xnor = (ones_count > 4) || ((ones_count == 4) && (data_i[0] == 1'b0));

wire [8:0] q_m_next;
assign q_m_next[0] = data_i[0];
assign q_m_next[1] = use_xnor ? ~(q_m_next[0] ^ data_i[1]) : (q_m_next[0] ^ data_i[1]);
assign q_m_next[2] = use_xnor ? ~(q_m_next[1] ^ data_i[2]) : (q_m_next[1] ^ data_i[2]);
assign q_m_next[3] = use_xnor ? ~(q_m_next[2] ^ data_i[3]) : (q_m_next[2] ^ data_i[3]);
assign q_m_next[4] = use_xnor ? ~(q_m_next[3] ^ data_i[4]) : (q_m_next[3] ^ data_i[4]);
assign q_m_next[5] = use_xnor ? ~(q_m_next[4] ^ data_i[5]) : (q_m_next[4] ^ data_i[5]);
assign q_m_next[6] = use_xnor ? ~(q_m_next[5] ^ data_i[6]) : (q_m_next[5] ^ data_i[6]);
assign q_m_next[7] = use_xnor ? ~(q_m_next[6] ^ data_i[7]) : (q_m_next[6] ^ data_i[7]);
assign q_m_next[8] = ~use_xnor;

reg [8:0] q_m;
always @(posedge clk_hdmi or negedge rst_n) begin
    if (!rst_n)
        q_m <= 9'b0;
    else if (!de)
        q_m <= 9'b0;
    else
        q_m <= q_m_next;
end


// Control signal encoding for blanking intervals
reg signed [4:0] disparity;
reg [3:0] dc_ones_cnt;
reg dc_invert;
reg [3:0] dc_n1_final;
reg [9:0] tmds_next;

always @(posedge clk_hdmi or negedge rst_n) begin
    if(!rst_n) begin
        tmds_o <= 10'b0;
        disparity <= 5'sd0;
    end
    else begin
        if (!de) begin
            // Output control codes during blanking intervals based on ctrl_i
            case (ctrl_i)
                2'b00: tmds_o <= 10'b1101010100; // Control code for blanking
                2'b01: tmds_o <= 10'b0010101011; // Control code for blanking
                2'b10: tmds_o <= 10'b0101010100; // Control code for blanking
                2'b11: tmds_o <= 10'b1010101011; // Control code for blanking
                default: tmds_o <= 10'b0;
            endcase
            disparity <= 5'sd0;

        end else begin
            // Update disparity based on the number of ones in the encoded data
            dc_ones_cnt = 
                q_m[0] + q_m[1] + q_m[2] + q_m[3] +
                q_m[4] + q_m[5] + q_m[6] + q_m[7];

            // Determine whether to invert the data based on the current disparity and the number of ones
            dc_invert = 
                (disparity == 0 || dc_ones_cnt == 4) ? ~q_m[8] : 
                    (disparity > 0) ? (dc_ones_cnt > 4) : (dc_ones_cnt < 4);

            // Build next TMDS symbol first so disparity uses same-cycle value.
            tmds_next[9] = dc_invert;
            tmds_next[8] = q_m[8];
            tmds_next[7:0] = dc_invert ? ~q_m[7:0] : q_m[7:0];

            tmds_o <= tmds_next;

            // Update disparity counter based on the number of ones in the output
            dc_n1_final = 
                tmds_next[9] + tmds_next[8] + tmds_next[7] + tmds_next[6] +
                tmds_next[5] + tmds_next[4] + tmds_next[3] + tmds_next[2] +
                tmds_next[1] + tmds_next[0];

            disparity <= disparity + 2*dc_n1_final - 10;
        end
    end
end
    
endmodule

hdmi_base/tb/tmds_encoder_golden_tb.v
`timescale 1ns/1ps

module tmds_encoder_golden_tb;

reg clk_hdmi;
reg rst_n;
reg de;
reg [7:0] data_i;
reg [1:0] ctrl_i;
wire [9:0] tmds_o;

integer i;

tmds_encoder dut (
    .clk_hdmi(clk_hdmi),
    .rst_n(rst_n),
    .de(de),
    .data_i(data_i),
    .ctrl_i(ctrl_i),
    .tmds_o(tmds_o)
);

always #5 clk_hdmi = ~clk_hdmi;

reg [8:0] ref_q_m;
reg signed [4:0] ref_disparity;

function [3:0] count_ones8;
    input [7:0] v;
    integer k;
    begin
        count_ones8 = 4'd0;
        for (k = 0; k < 8; k = k + 1)
            count_ones8 = count_ones8 + v[k];
    end
endfunction

function [3:0] count_ones10;
    input [9:0] v;
    integer k;
    begin
        count_ones10 = 4'd0;
        for (k = 0; k < 10; k = k + 1)
            count_ones10 = count_ones10 + v[k];
    end
endfunction

function [8:0] qm_from_data;
    input [7:0] d;
    reg use_xnor;
    reg [8:0] q;
    begin
        use_xnor = (count_ones8(d) > 4) || ((count_ones8(d) == 4) && (d[0] == 1'b0));
        q[0] = d[0];
        q[1] = use_xnor ? ~(q[0] ^ d[1]) : (q[0] ^ d[1]);
        q[2] = use_xnor ? ~(q[1] ^ d[2]) : (q[1] ^ d[2]);
        q[3] = use_xnor ? ~(q[2] ^ d[3]) : (q[2] ^ d[3]);
        q[4] = use_xnor ? ~(q[3] ^ d[4]) : (q[3] ^ d[4]);
        q[5] = use_xnor ? ~(q[4] ^ d[5]) : (q[4] ^ d[5]);
        q[6] = use_xnor ? ~(q[5] ^ d[6]) : (q[5] ^ d[6]);
        q[7] = use_xnor ? ~(q[6] ^ d[7]) : (q[6] ^ d[7]);
        q[8] = ~use_xnor;
        qm_from_data = q;
    end
endfunction

task automatic apply_and_check;
    input step_rst_n;
    input step_de;
    input [7:0] step_data;
    input [1:0] step_ctrl;
    reg [9:0] expected;
    reg [9:0] sym;
    reg dc_invert;
    reg [3:0] dc_ones;
    reg [3:0] dc_n1_final;
    reg [8:0] next_q_m;
    reg signed [4:0] next_disparity;
    begin
        rst_n = step_rst_n;
        de = step_de;
        data_i = step_data;
        ctrl_i = step_ctrl;

        if (!step_rst_n) begin
            expected = 10'b0000000000;
            next_q_m = 9'b000000000;
            next_disparity = 5'sd0;
        end else if (!step_de) begin
            case (step_ctrl)
                2'b00: expected = 10'b1101010100;
                2'b01: expected = 10'b0010101011;
                2'b10: expected = 10'b0101010100;
                default: expected = 10'b1010101011;
            endcase
            next_q_m = 9'b000000000;
            next_disparity = 5'sd0;
        end else begin
            dc_ones = ref_q_m[0] + ref_q_m[1] + ref_q_m[2] + ref_q_m[3] +
                      ref_q_m[4] + ref_q_m[5] + ref_q_m[6] + ref_q_m[7];

            dc_invert = (ref_disparity == 0 || dc_ones == 4) ? ~ref_q_m[8] :
                        ((ref_disparity > 0) ? (dc_ones > 4) : (dc_ones < 4));

            sym[9] = dc_invert;
            sym[8] = ref_q_m[8];
            sym[7:0] = dc_invert ? ~ref_q_m[7:0] : ref_q_m[7:0];

            expected = sym;
            dc_n1_final = count_ones10(sym);
            next_disparity = ref_disparity + (dc_n1_final <<< 1) - 10;
            next_q_m = qm_from_data(step_data);
        end

        @(posedge clk_hdmi);
        #1;

        if (tmds_o !== expected) begin
            $display("ERROR @%0t: rst_n=%b de=%b data=%h ctrl=%b expected=%b got=%b ref_qm=%b ref_disp=%0d",
                $time, step_rst_n, step_de, step_data, step_ctrl, expected, tmds_o, ref_q_m, ref_disparity);
            $finish;
        end

        ref_q_m = next_q_m;
        ref_disparity = next_disparity;
    end
endtask

initial begin
    clk_hdmi = 1'b0;
    rst_n = 1'b0;
    de = 1'b0;
    data_i = 8'h00;
    ctrl_i = 2'b00;
    ref_q_m = 9'b0;
    ref_disparity = 5'sd0;

    $dumpfile("tb/tmds_encoder_golden_tb.vcd");
    $dumpvars(0, tmds_encoder_golden_tb);

    apply_and_check(1'b0, 1'b0, 8'h00, 2'b00);
    apply_and_check(1'b0, 1'b0, 8'h00, 2'b00);

    apply_and_check(1'b1, 1'b0, 8'h00, 2'b00);
    apply_and_check(1'b1, 1'b0, 8'h00, 2'b01);
    apply_and_check(1'b1, 1'b0, 8'h00, 2'b10);
    apply_and_check(1'b1, 1'b0, 8'h00, 2'b11);

    apply_and_check(1'b1, 1'b1, 8'h00, 2'b00);
    apply_and_check(1'b1, 1'b1, 8'hff, 2'b00);
    apply_and_check(1'b1, 1'b1, 8'h55, 2'b00);
    apply_and_check(1'b1, 1'b1, 8'haa, 2'b00);
    apply_and_check(1'b1, 1'b1, 8'h0f, 2'b00);
    apply_and_check(1'b1, 1'b1, 8'hf0, 2'b00);

    for (i = 0; i < 128; i = i + 1)
        apply_and_check(1'b1, 1'b1, $random, 2'b00);

    apply_and_check(1'b0, 1'b1, 8'h00, 2'b00);
    apply_and_check(1'b1, 1'b0, 8'h00, 2'b00);

    $display("PASS: tmds_encoder golden comparison completed.");
    repeat (2) @(posedge clk_hdmi);
    $finish;
end

endmodule

hdmi_base/tb/tmds_encoder_golden_tb.vcd
$date
	Tue Apr 07 04:23:29 2026
$end
$version
	Icarus Verilog
$end
$timescale
	1ps
$end
$scope module tmds_encoder_golden_tb $end
$var wire 10 ! tmds_o [9:0] $end
$var reg 1 " clk_hdmi $end
$var reg 2 # ctrl_i [1:0] $end
$var reg 8 $ data_i [7:0] $end
$var reg 1 % de $end
$var reg 5 & ref_disparity [4:0] $end
$var reg 9 ' ref_q_m [8:0] $end
$var reg 1 ( rst_n $end
$var integer 32 ) i [31:0] $end
$scope function count_ones10 $end
$var reg 10 * v [9:0] $end
$var integer 32 + k [31:0] $end
$upscope $end
$scope function count_ones8 $end
$var reg 8 , v [7:0] $end
$var integer 32 - k [31:0] $end
$upscope $end
$scope function qm_from_data $end
$var reg 8 . d [7:0] $end
$var reg 9 / q [8:0] $end
$var reg 1 0 use_xnor $end
$upscope $end
$scope module dut $end
$var wire 1 " clk_hdmi $end
$var wire 2 1 ctrl_i [1:0] $end
$var wire 8 2 data_i [7:0] $end
$var wire 1 % de $end
$var wire 1 ( rst_n $end
$var wire 1 3 use_xnor $end
$var wire 9 4 q_m_next [8:0] $end
$var wire 4 5 ones_count [3:0] $end
$var reg 1 6 dc_invert $end
$var reg 4 7 dc_n1_final [3:0] $end
$var reg 4 8 dc_ones_cnt [3:0] $end
$var reg 5 9 disparity [4:0] $end
$var reg 9 : q_m [8:0] $end
$var reg 10 ; tmds_next [9:0] $end
$var reg 10 < tmds_o [9:0] $end
$upscope $end
$scope task apply_and_check $end
$upscope $end
$upscope $end
$enddefinitions $end
$comment Show the parameter values. $end
$dumpall
$end
#0
$dumpvars
b0 <
bx ;
b0 :
b0 9
bx 8
bx 7
x6
b0 5
b100000000 4
03
b0 2
b0 1
x0
bx /
bx .
bx -
bx ,
bx +
bx *
bx )
0(
b0 '
b0 &
0%
b0 $
b0 #
0"
b0 !
$end
#5000
1"
#10000
0"
#15000
1"
#16000
1(
#20000
0"
#25000
b1101010100 !
b1101010100 <
1"
#26000
b1 #
b1 1
#30000
0"
#35000
b10101011 !
b10101011 <
1"
#36000
b10 #
b10 1
#40000
0"
#45000
b101010100 !
b101010100 <
1"
#46000
b11 #
b11 1
#50000
0"
#55000
b1010101011 !
b1010101011 <
1"
#56000
b100000000 /
00
b1000 -
b0 ,
b0 .
b1010 +
b1011111111 *
b0 #
b0 1
1%
#60000
0"
#65000
b1000 9
b1011111111 !
b1011111111 <
b100000000 :
b1001 7
b1011111111 ;
16
b0 8
1"
#66000
13
b1000 5
b11111111 4
b11111111 /
10
b1000 -
b11111111 ,
b11111111 .
b1010 +
b100000000 *
b11111111 $
b11111111 2
b1000 &
b100000000 '
#70000
0"
#75000
b11111111 :
b0 9
b100000000 !
b100000000 <
b1 7
b100000000 ;
06
1"
#76000
b100110011 4
03
b100 5
b100110011 /
00
b1000 -
b1010101 ,
b1010101 .
b1010 +
b1000000000 *
b1010101 $
b1010101 2
b0 &
b11111111 '
#80000
0"
#85000
b11000 9
b1000000000 !
b1000000000 <
b100110011 :
b1000000000 ;
16
b1000 8
1"
#86000
13
b100 5
b11001100 4
b11001100 /
10
b1000 -
b10101010 ,
b10101010 .
b1010 +
b100110011 *
b10101010 $
b10101010 2
b11000 &
b100110011 '
#90000
0"
#95000
b11001100 :
b100110011 !
b100110011 <
b101 7
b100110011 ;
06
b100 8
1"
#96000
03
b100 5
b100000101 4
b100000101 /
00
b1000 -
b1111 ,
b1111 .
b1010 +
b1000110011 *
b1111 $
b1111 2
b11001100 '
#100000
0"
#105000
b1000110011 !
b1000110011 <
b100000101 :
b1000110011 ;
16
1"
#106000
13
b100 5
b11111010 4
b11111010 /
10
b1000 -
b11110000 ,
b11110000 .
b1010 +
b1111111010 *
b11110000 $
b11110000 2
b100000101 '
#110000
0"
#115000
b11111010 :
b11110 9
b1111111010 !
b1111111010 <
b1000 7
b1111111010 ;
b10 8
1"
#116000
b100011100 4
03
b10 5
b100011100 /
00
b1000 -
b100100 ,
b100100 .
b1010 +
b11111010 *
b100100 $
b100100 2
b0 )
b11110 &
b11111010 '
#120000
0"
#125000
b0 9
b11111010 !
b11111010 <
b100011100 :
b110 7
b11111010 ;
06
b110 8
1"
#126000
b10 5
b101111111 4
b101111111 /
b1000 -
b10000001 ,
b10000001 .
b1010 +
b100011100 *
b10000001 $
b10000001 2
b1 )
b0 &
b100011100 '
#130000
0"
#135000
b101111111 :
b11110 9
b100011100 !
b100011100 <
b100 7
b100011100 ;
b11 8
1"
#136000
b100000111 4
b10 5
b100000111 /
b1000 -
b1001 ,
b1001 .
b1010 +
b101111111 *
b1001 $
b1001 2
b10 )
b11110 &
b101111111 '
#140000
0"
#145000
b100 9
b101111111 !
b101111111 <
b100000111 :
b1000 7
b101111111 ;
b111 8
1"
#146000
b100100001 4
b100 5
b100100001 /
b1000 -
b1100011 ,
b1100011 .
b1010 +
b100000111 *
b1100011 $
b1100011 2
b11 )
b100 &
b100000111 '
#150000
0"
#155000
b100100001 :
b10 9
b100000111 !
b100000111 <
b100 7
b100000111 ;
b11 8
1"
#156000
b111111011 4
b11 5
b111111011 /
b1000 -
b1101 ,
b1101 .
b1010 +
b100100001 *
b1101 $
b1101 2
b100 )
b10 &
b100100001 '
#160000
0"
#165000
b11110 9
b100100001 !
b100100001 <
b111111011 :
b11 7
b100100001 ;
b10 8
1"
#166000
b101111011 4
b100 5
b101111011 /
b1000 -
b10001101 ,
b10001101 .
b1010 +
b111111011 *
b10001101 $
b10001101 2
b101 )
b11110 &
b111111011 '
#170000
0"
#175000
b101111011 :
b100 9
b111111011 !
b111111011 <
b1000 7
b111111011 ;
b111 8
1"
#176000
b100100011 4
b100 5
b100100011 /
b1000 -
b1100101 ,
b1100101 .
b1010 +
b1110000100 *
b1100101 $
b1100101 2
b110 )
b100 &
b101111011 '
#180000
0"
#185000
b10 9
b1110000100 !
b1110000100 <
b100100011 :
b100 7
b1110000100 ;
16
b110 8
1"
#186000
b10 5
b100001110 4
b100001110 /
b1000 -
b10010 ,
b10010 .
b1010 +
b100100011 *
b10010 $
b10010 2
b111 )
b10 &
b100100011 '
#190000
0"
#195000
b100001110 :
b0 9
b100100011 !
b100100011 <
b100100011 ;
06
b11 8
1"
#196000
b1 5
b111111111 4
b111111111 /
b1000 -
b1 ,
b1 .
b1010 +
b100001110 *
b1 $
b1 2
b1000 )
b0 &
b100001110 '
#200000
0"
#205000
b11110 9
b100001110 !
b100001110 <
b111111111 :
b100001110 ;
1"
#206000
b111111011 4
b11 5
b111111011 /
b1000 -
b1101 ,
b1101 .
b1010 +
b111111111 *
b1101 $
b1101 2
b1001 )
b11110 &
b111111111 '
#210000
0"
#215000
b111111011 :
b110 9
b111111111 !
b111111111 <
b1001 7
b111111111 ;
b1000 8
1"
#216000
13
b101 5
b1111000 4
b1111000 /
10
b1000 -
b1110110 ,
b1110110 .
b1010 +
b1100000100 *
b1110110 $
b1110110 2
b1010 )
b110 &
b111111011 '
#220000
0"
#225000
b10 9
b1100000100 !
b1100000100 <
b1111000 :
b11 7
b1100000100 ;
16
b111 8
1"
#226000
b101 5
b1000001 4
b1000001 /
b1000 -
b111101 ,
b111101 .
b1010 +
b1010000111 *
b111101 $
b111101 2
b1011 )
b10 &
b1111000 '
#230000
0"
#235000
b1000001 :
b1010000111 !
b1010000111 <
b101 7
b1010000111 ;
b100 8
1"
#236000
b11110001 4
b110 5
b11110001 /
b1000 -
b11101101 ,
b11101101 .
b1010 +
b1000001 *
b11101101 $
b11101101 2
b1100 )
b1000001 '
#240000
0"
#245000
b11100 9
b1000001 !
b1000001 <
b11110001 :
b10 7
b1000001 ;
06
b10 8
1"
#246000
03
b11 5
b110000100 4
b110000100 /
00
b1000 -
b10001100 ,
b10001100 .
b1010 +
b11110001 *
b10001100 $
b10001100 2
b1101 )
b11100 &
b11110001 '
#250000
0"
#255000
b110000100 :
b11110001 !
b11110001 <
b101 7
b11110001 ;
b101 8
1"
#256000
13
b110 5
b11111101 4
b11111101 /
10
b1000 -
b11111001 ,
b11111001 .
b1010 +
b1101111011 *
b11111001 $
b11111001 2
b1110 )
b110000100 '
#260000
0"
#265000
b10 9
b1101111011 !
b1101111011 <
b11111101 :
b1000 7
b1101111011 ;
16
b10 8
1"
#266000
b100 5
b11101000 4
b11101000 /
b1000 -
b11000110 ,
b11000110 .
b1010 +
b1000000010 *
b11000110 $
b11000110 2
b1111 )
b10 &
b11111101 '
#270000
0"
#275000
b11101000 :
b11100 9
b1000000010 !
b1000000010 <
b10 7
b1000000010 ;
b111 8
1"
#276000
03
b100 5
b101000011 4
b101000011 /
00
b1000 -
b11000101 ,
b11000101 .
b1010 +
b1000010111 *
b11000101 $
b11000101 2
b10000 )
b11100 &
b11101000 '
#280000
0"
#285000
b1000010111 !
b1000010111 <
b101000011 :
b101 7
b1000010111 ;
b100 8
1"
#286000
13
b100 5
b11001100 4
b11001100 /
10
b1000 -
b10101010 ,
b10101010 .
b1010 +
b1110111100 *
b10101010 $
b10101010 2
b10001 )
b101000011 '
#290000
0"
#295000
b11001100 :
b0 9
b1110111100 !
b1110111100 <
b111 7
b1110111100 ;
b11 8
1"
#296000
b101 5
b1001 4
b1001 /
b1000 -
b11100101 ,
b11100101 .
b1010 +
b1000110011 *
b11100101 $
b11100101 2
b10010 )
b0 &
b11001100 '
#300000
0"
#305000
b1000110011 !
b1000110011 <
b1001 :
b101 7
b1000110011 ;
b100 8
1"
#306000
b10000111 4
b110 5
b10000111 /
b1000 -
b1110111 ,
b1110111 .
b1010 +
b1011110110 *
b1110111 $
b1110111 2
b10011 )
b1001 '
#310000
0"
#315000
b10000111 :
b100 9
b1011110110 !
b1011110110 <
b111 7
b1011110110 ;
b10 8
1"
#316000
03
b10 5
b100001110 4
b100001110 /
00
b1000 -
b10010 ,
b10010 .
b1010 +
b1001111000 *
b10010 $
b10010 2
b10100 )
b100 &
b10000111 '
#320000
0"
#325000
b1001111000 !
b1001111000 <
b100001110 :
b101 7
b1001111000 ;
b100 8
1"
#326000
13
b101 5
b101111 4
b101111 /
10
b1000 -
b10001111 ,
b10001111 .
b1010 +
b100001110 *
b10001111 $
b10001111 2
b10101 )
b100001110 '
#330000
0"
#335000
b101111 :
b10 9
b100001110 !
b100001110 <
b100 7
b100001110 ;
06
b11 8
1"
#336000
b101 5
b100 4
b100 /
b1000 -
b11110010 ,
b11110010 .
b1010 +
b1011010000 *
b11110010 $
b11110010 2
b10110 )
b10 &
b101111 '
#340000
0"
#345000
b0 9
b1011010000 !
b1011010000 <
b100 :
b1011010000 ;
16
b101 8
1"
#346000
b10000 4
b101 5
b10000 /
b1000 -
b11001110 ,
b11001110 .
b1010 +
b1011111011 *
b11001110 $
b11001110 2
b10111 )
b0 &
b100 '
#350000
0"
#355000
b10000 :
b110 9
b1011111011 !
b1011111011 <
b1000 7
b1011111011 ;
b1 8
1"
#356000
b11110010 4
b100 5
b11110010 /
b1000 -
b11101000 ,
b11101000 .
b1010 +
b10000 *
b11101000 $
b11101000 2
b11000 )
b110 &
b10000 '
#360000
0"
#365000
b11110 9
b10000 !
b10000 <
b11110010 :
b1 7
b10000 ;
06
1"
#366000
03
b100 5
b101000011 4
b101000011 /
00
b1000 -
b11000101 ,
b11000101 .
b1010 +
b11110010 *
b11000101 $
b11000101 2
b11001 )
b11110 &
b11110010 '
#370000
0"
#375000
b101000011 :
b11110010 !
b11110010 <
b101 7
b11110010 ;
b101 8
1"
#376000
13
b100 5
b10011110 4
b10011110 /
10
b1000 -
b1011100 ,
b1011100 .
b1010 +
b1110111100 *
b1011100 $
b1011100 2
b11010 )
b101000011 '
#380000
0"
#385000
b10 9
b1110111100 !
b1110111100 <
b10011110 :
b111 7
b1110111100 ;
16
b11 8
1"
#386000
b110 5
b11000001 4
b11000001 /
b1000 -
b10111101 ,
b10111101 .
b1010 +
b1001100001 *
b10111101 $
b10111101 2
b11011 )
b10 &
b10011110 '
#390000
0"
#395000
b11000001 :
b0 9
b1001100001 !
b1001100001 <
b100 7
b1001100001 ;
b101 8
1"
#396000
b100011011 4
03
b100 5
b100011011 /
00
b1000 -
b101101 ,
b101101 .
b1010 +
b1000111110 *
b101101 $
b101101 2
b11100 )
b0 &
b11000001 '
#400000
0"
#405000
b10 9
b1000111110 !
b1000111110 <
b100011011 :
b110 7
b1000111110 ;
b11 8
1"
#406000
b100100011 4
b100 5
b100100011 /
b1000 -
b1100101 ,
b1100101 .
b1010 +
b100011011 *
b1100101 $
b1100101 2
b11101 )
b10 &
b100011011 '
#410000
0"
#415000
b100100011 :
b100011011 !
b100011011 <
b101 7
b100011011 ;
06
b100 8
1"
#416000
b100100001 4
b100 5
b100100001 /
b1000 -
b1100011 ,
b1100011 .
b1010 +
b100100011 *
b1100011 $
b1100011 2
b11110 )
b100100011 '
#420000
0"
#425000
b0 9
b100100011 !
b100100011 <
b100100001 :
b100 7
b100100011 ;
b11 8
1"
#426000
b10 5
b100000110 4
b100000110 /
b1000 -
b1010 ,
b1010 .
b1010 +
b100100001 *
b1010 $
b1010 2
b11111 )
b0 &
b100100001 '
#430000
0"
#435000
b100000110 :
b11100 9
b100100001 !
b100100001 <
b11 7
b100100001 ;
b10 8
1"
#436000
b110000000 4
b1 5
b110000000 /
b1000 -
b10000000 ,
b10000000 .
b1010 +
b1111111001 *
b10000000 $
b10000000 2
b100000 )
b11100 &
b100000110 '
#440000
0"
#445000
b10 9
b1111111001 !
b1111111001 <
b110000000 :
b1000 7
b1111111001 ;
16
1"
#446000
b111100000 4
b1 5
b111100000 /
b1000 -
b100000 ,
b100000 .
b1010 +
b110000000 *
b100000 $
b100000 2
b100001 )
b10 &
b110000000 '
#450000
0"
#455000
b111100000 :
b11100 9
b110000000 !
b110000000 <
b10 7
b110000000 ;
06
b1 8
1"
#456000
13
b11001100 4
b100 5
b11001100 /
10
b1000 -
b10101010 ,
b10101010 .
b1010 +
b1100011111 *
b10101010 $
b10101010 2
b100010 )
b11100 &
b111100000 '
#460000
0"
#465000
b0 9
b1100011111 !
b1100011111 <
b11001100 :
b111 7
b1100011111 ;
16
b11 8
1"
#466000
b101 5
b100001 4
b100001 /
b1000 -
b10011101 ,
b10011101 .
b1010 +
b1000110011 *
b10011101 $
b10011101 2
b100011 )
b0 &
b11001100 '
#470000
0"
#475000
b100001 :
b1000110011 !
b1000110011 <
b101 7
b1000110011 ;
b100 8
1"
#476000
b100 5
b11011000 4
b11011000 /
b1000 -
b10010110 ,
b10010110 .
b1010 +
b1011011110 *
b10010110 $
b10010110 2
b100100 )
b100001 '
#480000
0"
#485000
b100 9
b1011011110 !
b1011011110 <
b11011000 :
b111 7
b1011011110 ;
b10 8
1"
#486000
03
b11 5
b111110001 4
b111110001 /
00
b1000 -
b10011 ,
b10011 .
b1010 +
b1000100111 *
b10011 $
b10011 2
b100101 )
b100 &
b11011000 '
#490000
0"
#495000
b111110001 :
b1000100111 !
b1000100111 <
b101 7
b1000100111 ;
b100 8
1"
#496000
b111111011 4
b11 5
b111111011 /
b1000 -
b1101 ,
b1101 .
b1010 +
b1100001110 *
b1101 $
b1101 2
b100110 )
b111110001 '
#500000
0"
#505000
b1100001110 !
b1100001110 <
b111111011 :
b1100001110 ;
b101 8
1"
#506000
b100110001 4
b100 5
b100110001 /
b1000 -
b1010011 ,
b1010011 .
b1010 +
b1100000100 *
b1010011 $
b1010011 2
b100111 )
b111111011 '
#510000
0"
#515000
b100110001 :
b0 9
b1100000100 !
b1100000100 <
b11 7
b1100000100 ;
b111 8
1"
#516000
b1110011 4
13
b101 5
b1110011 /
10
b1000 -
b1101011 ,
b1101011 .
b1010 +
b100110001 *
b1101011 $
b1101011 2
b101000 )
b0 &
b100110001 '
#520000
0"
#525000
b11110 9
b100110001 !
b100110001 <
b1110011 :
b100 7
b100110001 ;
06
b11 8
1"
#526000
b11001 4
b101 5
b11001 /
b1000 -
b11010101 ,
b11010101 .
b1010 +
b1110011 *
b11010101 $
b11010101 2
b101001 )
b11110 &
b1110011 '
#530000
0"
#535000
b11001 :
b1110011 !
b1110011 <
b101 7
b1110011 ;
b101 8
1"
#536000
03
b1 5
b111111110 4
b111111110 /
00
b1000 -
b10 ,
b10 .
b1010 +
b1011100110 *
b10 $
b10 2
b101010 )
b11001 '
#540000
0"
#545000
b0 9
b1011100110 !
b1011100110 <
b111111110 :
b110 7
b1011100110 ;
16
b11 8
1"
#546000
b110000 4
13
b101 5
b110000 /
10
b1000 -
b10101110 ,
b10101110 .
b1010 +
b111111110 *
b10101110 $
b10101110 2
b101011 )
b0 &
b111111110 '
#550000
0"
#555000
b110000 :
b110 9
b111111110 !
b111111110 <
b1000 7
b111111110 ;
06
b111 8
1"
#556000
03
b100 5
b100001011 4
b100001011 /
00
b1000 -
b11101 ,
b11101 .
b1010 +
b110000 *
b11101 $
b11101 2
b101100 )
b110 &
b110000 '
#560000
0"
#565000
b0 9
b110000 !
b110000 <
b100001011 :
b10 7
b110000 ;
b10 8
1"
#566000
b11101111 4
13
b110 5
b11101111 /
10
b1000 -
b11001111 ,
b11001111 .
b1010 +
b100001011 *
b11001111 $
b11001111 2
b101101 )
b0 &
b100001011 '
#570000
0"
#575000
b11101111 :
b11110 9
b100001011 !
b100001011 <
b100 7
b100001011 ;
b11 8
1"
#576000
b111100001 4
03
b11 5
b111100001 /
00
b1000 -
b100011 ,
b100011 .
b1010 +
b11101111 *
b100011 $
b100011 2
b101110 )
b11110 &
b11101111 '
#580000
0"
#585000
b10 9
b11101111 !
b11101111 <
b111100001 :
b111 7
b11101111 ;
b111 8
1"
#586000
b10 5
b100000110 4
b100000110 /
b1000 -
b1010 ,
b1010 .
b1010 +
b111100001 *
b1010 $
b1010 2
b101111 )
b10 &
b111100001 '
#590000
0"
#595000
b100000110 :
b111100001 !
b111100001 <
b101 7
b111100001 ;
b100 8
1"
#596000
13
b11101100 4
b100 5
b11101100 /
10
b1000 -
b11001010 ,
b11001010 .
b1010 +
b100000110 *
b11001010 $
b11001010 2
b110000 )
b100000110 '
#600000
0"
#605000
b11110 9
b100000110 !
b100000110 <
b11101100 :
b11 7
b100000110 ;
b10 8
1"
#606000
b10111110 4
b100 5
b10111110 /
b1000 -
b111100 ,
b111100 .
b1010 +
b11101100 *
b111100 $
b111100 2
b110001 )
b11110 &
b11101100 '
#610000
0"
#615000
b10111110 :
b11101100 !
b11101100 <
b101 7
b11101100 ;
b101 8
1"
#616000
b100 4
b101 5
b100 /
b1000 -
b11110010 ,
b11110010 .
b1010 +
b10111110 *
b11110010 $
b11110010 2
b110010 )
b10111110 '
#620000
0"
#625000
b0 9
b10111110 !
b10111110 <
b100 :
b110 7
b10111110 ;
b110 8
1"
#626000
b110000110 4
03
b11 5
b110000110 /
00
b1000 -
b10001010 ,
b10001010 .
b1010 +
b1011111011 *
b10001010 $
b10001010 2
b110011 )
b0 &
b100 '
#630000
0"
#635000
b110000110 :
b110 9
b1011111011 !
b1011111011 <
b1000 7
b1011111011 ;
16
b1 8
1"
#636000
b10 5
b100111111 4
b100111111 /
b1000 -
b1000001 ,
b1000001 .
b1010 +
b110000110 *
b1000001 $
b1000001 2
b110100 )
b110 &
b110000110 '
#640000
0"
#645000
b100 9
b110000110 !
b110000110 <
b100111111 :
b100 7
b110000110 ;
06
b11 8
1"
#646000
13
b100 5
b11100010 4
b11100010 /
10
b1000 -
b11011000 ,
b11011000 .
b1010 +
b1111000000 *
b11011000 $
b11011000 2
b110101 )
b100 &
b100111111 '
#650000
0"
#655000
b11100010 :
b10 9
b1111000000 !
b1111000000 <
b1111000000 ;
16
b110 8
1"
#656000
b10000010 4
b100 5
b10000010 /
b1000 -
b1111000 ,
b1111000 .
b1010 +
b1000011101 *
b1111000 $
b1111000 2
b110110 )
b10 &
b11100010 '
#660000
0"
#665000
b1000011101 !
b1000011101 <
b10000010 :
b101 7
b1000011101 ;
b100 8
1"
#666000
03
b11 5
b110000111 4
b110000111 /
00
b1000 -
b10001001 ,
b10001001 .
b1010 +
b10000010 *
b10001001 $
b10001001 2
b110111 )
b10000010 '
#670000
0"
#675000
b110000111 :
b11100 9
b10000010 !
b10000010 <
b10 7
b10000010 ;
06
b10 8
1"
#676000
b11110011 4
13
b110 5
b11110011 /
10
b1000 -
b11101011 ,
b11101011 .
b1010 +
b110000111 *
b11101011 $
b11101011 2
b111000 )
b11100 &
b110000111 '
#680000
0"
#685000
b110000111 !
b110000111 <
b11110011 :
b101 7
b110000111 ;
b100 8
1"
#686000
b101 5
b111000 4
b111000 /
b1000 -
b10110110 ,
b10110110 .
b1010 +
b11110011 *
b10110110 $
b10110110 2
b111001 )
b11110011 '
#690000
0"
#695000
b111000 :
b11110 9
b11110011 !
b11110011 <
b110 7
b11110011 ;
b110 8
1"
#696000
b11101000 4
b100 5
b11101000 /
b1000 -
b11000110 ,
b11000110 .
b1010 +
b1011000111 *
b11000110 $
b11000110 2
b111010 )
b11110 &
b111000 '
#700000
0"
#705000
b0 9
b1011000111 !
b1011000111 <
b11101000 :
b1011000111 ;
16
b11 8
1"
#706000
b110000 4
b101 5
b110000 /
b1000 -
b10101110 ,
b10101110 .
b1010 +
b1000010111 *
b10101110 $
b10101110 2
b111011 )
b0 &
b11101000 '
#710000
0"
