hdmi_base/src/vid_timing_gen.v
module vid_timing_gen #(
    parameter H_ACTIVE = 1280,
    parameter H_FRONT_PORCH = 110,
    parameter H_SYNC_PULSE = 40,
    parameter H_BACK_PORCH = 220,

    parameter V_ACTIVE = 720,
    parameter V_FRONT_PORCH = 5,
    parameter V_SYNC_PULSE = 5,
    parameter V_BACK_PORCH = 20
)(
    input wire clk_hdmi,
    input wire rst_n,

    output reg hsync,
    output reg vsync,
    output reg de,
    output reg [11:0] x,
    output reg [11:0] y,
    output wire frame_end
);

// Calculate total horizontal and vertical timings
localparam H_TOTAL = H_ACTIVE + H_FRONT_PORCH + H_SYNC_PULSE + H_BACK_PORCH;
localparam V_TOTAL = V_ACTIVE + V_FRONT_PORCH + V_SYNC_PULSE + V_BACK_PORCH;
localparam H_SYNC_START = H_ACTIVE + H_FRONT_PORCH;
localparam H_SYNC_END = H_ACTIVE + H_FRONT_PORCH + H_SYNC_PULSE;
localparam V_SYNC_START = V_ACTIVE + V_FRONT_PORCH;
localparam V_SYNC_END = V_ACTIVE + V_FRONT_PORCH + V_SYNC_PULSE;

// Internal counters for horizontal and vertical timings
reg [11:0] h_cnt;
reg [11:0] v_cnt;


// Generate horizontal and vertical counters
always @(posedge clk_hdmi or negedge rst_n) begin
    if (!rst_n) begin
        h_cnt <= 12'h0;
        v_cnt <= 12'h0;
    end else begin
        if (h_cnt < H_TOTAL - 12'h1) begin
            h_cnt <= h_cnt + 12'h1;
        end else begin
            h_cnt <= 12'h0;
            if (v_cnt < V_TOTAL - 12'h1) begin
                v_cnt <= v_cnt + 12'h1;
            end else begin
                v_cnt <= 12'h0;
            end
        end
    end
end

// Generate synchronization signals and data enable
function is_in_range;
    input [11:0] val; input [11:0] min; input [11:0] max;
    begin
        is_in_range = (val >= min) && (val <= max);
    end
endfunction
always @(posedge clk_hdmi or negedge rst_n) begin
    if(!rst_n) begin
        vsync <= 1'b0;
        hsync <= 1'b0;
        de <= 1'b0;
        x <= 12'd0;
        y <= 12'd0;
    end
    else begin
        hsync <= is_in_range(h_cnt, H_SYNC_START, H_SYNC_END - 12'h1);
        vsync <= is_in_range(v_cnt, V_SYNC_START, V_SYNC_END - 12'h1);
        de <= (h_cnt < H_ACTIVE) && (v_cnt < V_ACTIVE);
        x <= h_cnt;
        y <= v_cnt;
    end
end

// Generate frame end signal when both horizontal and vertical counters reach their maximum values
assign frame_end = (h_cnt == H_TOTAL - 12'h1) && (v_cnt == V_TOTAL - 12'h1);

endmodule

hdmi_base/tb/vid_timing_gen_tb.v
`timescale 1ns/1ps

module vid_timing_gen_tb;

localparam FRAME_TARGET = 3;

localparam H_ACTIVE = 8;
localparam H_FRONT_PORCH = 2;
localparam H_SYNC_PULSE = 2;
localparam H_BACK_PORCH = 2;
localparam H_TOTAL = H_ACTIVE + H_FRONT_PORCH + H_SYNC_PULSE + H_BACK_PORCH;

localparam V_ACTIVE = 4;
localparam V_FRONT_PORCH = 1;
localparam V_SYNC_PULSE = 1;
localparam V_BACK_PORCH = 1;
localparam V_TOTAL = V_ACTIVE + V_FRONT_PORCH + V_SYNC_PULSE + V_BACK_PORCH;

reg clk_hdmi;
reg rst_n;

wire hsync;
wire vsync;
wire de;
wire [11:0] x;
wire [11:0] y;
wire frame_end;

integer frame_count;
integer active_pixel_count;
integer total_pixel_count;
integer line_start_count;

vid_timing_gen #(
    .H_ACTIVE(H_ACTIVE),
    .H_FRONT_PORCH(H_FRONT_PORCH),
    .H_SYNC_PULSE(H_SYNC_PULSE),
    .H_BACK_PORCH(H_BACK_PORCH),
    .V_ACTIVE(V_ACTIVE),
    .V_FRONT_PORCH(V_FRONT_PORCH),
    .V_SYNC_PULSE(V_SYNC_PULSE),
    .V_BACK_PORCH(V_BACK_PORCH)
) uut (
    .clk_hdmi(clk_hdmi),
    .rst_n(rst_n),
    .hsync(hsync),
    .vsync(vsync),
    .de(de),
    .x(x),
    .y(y),
    .frame_end(frame_end)
);

always #5 clk_hdmi = ~clk_hdmi;

always @(posedge clk_hdmi) begin
    if (!rst_n) begin
        frame_count <= 0;
        active_pixel_count <= 0;
        total_pixel_count <= 0;
        line_start_count <= 0;
    end else begin
        total_pixel_count <= total_pixel_count + 1;

        if (x == 0)
            line_start_count <= line_start_count + 1;

        if (de)
            active_pixel_count <= active_pixel_count + 1;

        if (frame_end) begin
            frame_count <= frame_count + 1;
            $display("frame %0d end at time=%0t h_cnt=%0d v_cnt=%0d x=%0d y=%0d active_pixels=%0d total_pixels=%0d lines=%0d",
                frame_count + 1,
                $time,
                uut.h_cnt,
                uut.v_cnt,
                x,
                y,
                active_pixel_count,
                total_pixel_count,
                line_start_count
            );
            active_pixel_count <= 0;
            total_pixel_count <= 0;
            line_start_count <= 0;
        end
    end
end

initial begin
    clk_hdmi = 1'b0;
    rst_n = 1'b0;
    frame_count = 0;
    active_pixel_count = 0;

    $dumpfile("tb/vid_timing_gen_tb.vcd");
    $dumpvars(0, vid_timing_gen_tb);

    repeat (4) @(posedge clk_hdmi);
    rst_n = 1'b1;

    wait (frame_count == FRAME_TARGET);
    repeat (4) @(posedge clk_hdmi);
    $finish;
end

always @(posedge clk_hdmi) begin
    if (rst_n && frame_end && (uut.h_cnt != H_TOTAL - 1 || uut.v_cnt != V_TOTAL - 1)) begin
        $display("ERROR: frame_end asserted at wrong position time=%0t h_cnt=%0d v_cnt=%0d x=%0d y=%0d",
            $time,
            uut.h_cnt,
            uut.v_cnt,
            x,
            y
        );
        $finish;
    end

    if (rst_n && de && (x >= H_ACTIVE || y >= V_ACTIVE)) begin
        $display("ERROR: de asserted outside active area at time=%0t x=%0d y=%0d", $time, x, y);
        $finish;
    end

    if (rst_n && hsync && (x < H_ACTIVE + H_FRONT_PORCH || x >= H_ACTIVE + H_FRONT_PORCH + H_SYNC_PULSE)) begin
        $display("ERROR: hsync outside expected range at time=%0t x=%0d", $time, x);
        $finish;
    end

    if (rst_n && vsync && (y < V_ACTIVE + V_FRONT_PORCH || y >= V_ACTIVE + V_FRONT_PORCH + V_SYNC_PULSE)) begin
        $display("ERROR: vsync outside expected range at time=%0t y=%0d", $time, y);
        $finish;
    end
end

endmodule

hdmi_base/tb/vid_timing_gen_tb.vcd
$date
	Mon Apr 06 19:35:19 2026
$end
$version
	Icarus Verilog
$end
$timescale
	1ps
$end
$scope module vid_timing_gen_tb $end
$var wire 12 ! y [11:0] $end
$var wire 12 " x [11:0] $end
$var wire 1 # vsync $end
$var wire 1 $ hsync $end
$var wire 1 % frame_end $end
$var wire 1 & de $end
$var parameter 32 ' FRAME_TARGET $end
$var parameter 32 ( H_ACTIVE $end
$var parameter 32 ) H_BACK_PORCH $end
$var parameter 32 * H_FRONT_PORCH $end
$var parameter 32 + H_SYNC_PULSE $end
$var parameter 35 , H_TOTAL $end
$var parameter 32 - V_ACTIVE $end
$var parameter 32 . V_BACK_PORCH $end
$var parameter 32 / V_FRONT_PORCH $end
$var parameter 32 0 V_SYNC_PULSE $end
$var parameter 35 1 V_TOTAL $end
$var reg 1 2 clk_hdmi $end
$var reg 1 3 rst_n $end
$var integer 32 4 active_pixel_count [31:0] $end
$var integer 32 5 frame_count [31:0] $end
$var integer 32 6 line_start_count [31:0] $end
$var integer 32 7 total_pixel_count [31:0] $end
$scope module uut $end
$var wire 1 2 clk_hdmi $end
$var wire 1 % frame_end $end
$var wire 1 3 rst_n $end
$var parameter 32 8 H_ACTIVE $end
$var parameter 32 9 H_BACK_PORCH $end
$var parameter 32 : H_FRONT_PORCH $end
$var parameter 34 ; H_SYNC_END $end
$var parameter 32 < H_SYNC_PULSE $end
$var parameter 33 = H_SYNC_START $end
$var parameter 35 > H_TOTAL $end
$var parameter 32 ? V_ACTIVE $end
$var parameter 32 @ V_BACK_PORCH $end
$var parameter 32 A V_FRONT_PORCH $end
$var parameter 34 B V_SYNC_END $end
$var parameter 32 C V_SYNC_PULSE $end
$var parameter 33 D V_SYNC_START $end
$var parameter 35 E V_TOTAL $end
$var reg 1 & de $end
$var reg 12 F h_cnt [11:0] $end
$var reg 1 $ hsync $end
$var reg 12 G v_cnt [11:0] $end
$var reg 1 # vsync $end
$var reg 12 H x [11:0] $end
$var reg 12 I y [11:0] $end
$scope function is_in_range $end
$var reg 12 J max [11:0] $end
$var reg 12 K min [11:0] $end
$var reg 12 L val [11:0] $end
$upscope $end
$upscope $end
$upscope $end
$enddefinitions $end
$comment Show the parameter values. $end
$dumpall
b111 E
b101 D
b1 C
b110 B
b1 A
b1 @
b100 ?
b1110 >
b1010 =
b10 <
b1100 ;
b10 :
b10 9
b1000 8
b111 1
b1 0
b1 /
b1 .
b100 -
b1110 ,
b10 +
b10 *
b10 )
b1000 (
b11 '
$end
#0
$dumpvars
bx L
bx K
bx J
b0 I
b0 H
b0 G
b0 F
bx 7
bx 6
b0 5
b0 4
03
02
0&
0%
0$
0#
b0 "
b0 !
$end
#5000
b0 6
b0 7
12
#10000
02
#15000
12
#20000
02
#25000
12
#30000
02
#35000
b1 F
1&
b0 L
b101 K
b101 J
13
12
#40000
02
#45000
b1 "
b1 H
b10 F
b1 4
b1 6
b1 7
b0 L
b101 K
b101 J
12
#50000
02
#55000
b11 F
b10 "
b10 H
b10 4
b10 7
b0 L
b101 K
b101 J
12
#60000
02
#65000
b11 "
b11 H
b100 F
b11 4
b11 7
b0 L
b101 K
b101 J
12
#70000
02
#75000
b101 F
b100 "
b100 H
b100 4
b100 7
b0 L
b101 K
b101 J
12
#80000
02
#85000
b101 "
b101 H
b110 F
b101 4
b101 7
b0 L
b101 K
b101 J
12
#90000
02
#95000
b111 F
b110 "
b110 H
b110 4
b110 7
b0 L
b101 K
b101 J
12
#100000
02
#105000
b111 "
b111 H
b1000 F
b111 4
b111 7
b0 L
b101 K
b101 J
12
#110000
02
#115000
b1001 F
b1000 "
b1000 H
0&
b1000 4
b1000 7
b0 L
b101 K
b101 J
12
#120000
02
#125000
b1001 "
b1001 H
b1010 F
b1001 7
b0 L
b101 K
b101 J
12
#130000
02
#135000
b1011 F
b1010 "
b1010 H
1$
b1010 7
b0 L
b101 K
b101 J
12
#140000
02
#145000
b1011 "
b1011 H
b1100 F
b1011 7
b0 L
b101 K
b101 J
12
#150000
02
#155000
b1101 F
b1100 "
b1100 H
0$
b1100 7
b0 L
b101 K
b101 J
12
#160000
02
#165000
b1101 "
b1101 H
b1 G
b0 F
b1101 7
b0 L
b101 K
b101 J
12
#170000
02
#175000
b1 F
b1 !
b1 I
b0 "
b0 H
1&
b1110 7
b1 L
b101 K
b101 J
12
#180000
02
#185000
b1 "
b1 H
b10 F
b1001 4
b10 6
b1111 7
b101 K
b101 J
12
#190000
02
#195000
b11 F
b10 "
b10 H
b1010 4
b10000 7
b1 L
b101 K
b101 J
12
#200000
02
#205000
b11 "
b11 H
b100 F
b1011 4
b10001 7
b1 L
b101 K
b101 J
12
#210000
02
#215000
b101 F
b100 "
b100 H
b1100 4
b10010 7
b1 L
b101 K
b101 J
12
#220000
02
#225000
b101 "
b101 H
b110 F
b1101 4
b10011 7
b1 L
b101 K
b101 J
12
#230000
02
#235000
b111 F
b110 "
b110 H
b1110 4
b10100 7
b1 L
b101 K
b101 J
12
#240000
02
#245000
b111 "
b111 H
b1000 F
b1111 4
b10101 7
b1 L
b101 K
b101 J
12
#250000
02
#255000
b1001 F
b1000 "
b1000 H
0&
b10000 4
b10110 7
b1 L
b101 K
b101 J
12
#260000
02
#265000
b1001 "
b1001 H
b1010 F
b10111 7
b1 L
b101 K
b101 J
12
#270000
02
#275000
b1011 F
b1010 "
b1010 H
1$
b11000 7
b1 L
b101 K
b101 J
12
#280000
02
#285000
b1011 "
b1011 H
b1100 F
b11001 7
b1 L
b101 K
b101 J
12
#290000
02
#295000
b1101 F
b1100 "
b1100 H
0$
b11010 7
b1 L
b101 K
b101 J
12
#300000
02
#305000
b1101 "
b1101 H
b10 G
b0 F
b11011 7
b1 L
b101 K
b101 J
12
#310000
02
#315000
b1 F
b10 !
b10 I
b0 "
b0 H
1&
b11100 7
b10 L
b101 K
b101 J
12
#320000
02
#325000
b1 "
b1 H
b10 F
b10001 4
b11 6
b11101 7
b10 L
b101 K
b101 J
12
#330000
02
#335000
b11 F
b10 "
b10 H
b10010 4
b11110 7
b101 K
b101 J
12
#340000
02
#345000
b11 "
b11 H
b100 F
b10011 4
b11111 7
b10 L
b101 K
b101 J
12
#350000
02
#355000
b101 F
b100 "
b100 H
b10100 4
b100000 7
b10 L
b101 K
b101 J
12
#360000
02
#365000
b101 "
b101 H
b110 F
b10101 4
b100001 7
b10 L
b101 K
b101 J
12
#370000
02
#375000
b111 F
b110 "
b110 H
b10110 4
b100010 7
b10 L
b101 K
b101 J
12
#380000
02
#385000
b111 "
b111 H
b1000 F
b10111 4
b100011 7
b10 L
b101 K
b101 J
12
#390000
02
#395000
b1001 F
b1000 "
b1000 H
0&
b11000 4
b100100 7
b10 L
b101 K
b101 J
12
#400000
02
#405000
b1001 "
b1001 H
b1010 F
b100101 7
b10 L
b101 K
b101 J
12
#410000
02
#415000
b1011 F
b1010 "
b1010 H
1$
b100110 7
b10 L
b101 K
b101 J
12
#420000
02
#425000
b1011 "
b1011 H
b1100 F
b100111 7
b10 L
b101 K
b101 J
12
#430000
02
#435000
b1101 F
b1100 "
b1100 H
0$
b101000 7
b10 L
b101 K
b101 J
12
#440000
02
#445000
b1101 "
b1101 H
b11 G
b0 F
b101001 7
b10 L
b101 K
b101 J
12
#450000
02
#455000
b1 F
b11 !
b11 I
b0 "
b0 H
1&
b101010 7
b11 L
b101 K
b101 J
12
#460000
02
#465000
b1 "
b1 H
b10 F
b11001 4
b100 6
b101011 7
b11 L
b101 K
b101 J
12
#470000
02
#475000
b11 F
b10 "
b10 H
b11010 4
b101100 7
b11 L
b101 K
b101 J
12
#480000
02
#485000
b11 "
b11 H
b100 F
b11011 4
b101101 7
b101 K
b101 J
12
#490000
02
#495000
b101 F
b100 "
b100 H
b11100 4
b101110 7
b11 L
b101 K
b101 J
12
#500000
02
#505000
b101 "
b101 H
b110 F
b11101 4
b101111 7
b11 L
b101 K
b101 J
12
#510000
02
#515000
b111 F
b110 "
b110 H
b11110 4
b110000 7
b11 L
b101 K
b101 J
12
#520000
02
#525000
b111 "
b111 H
b1000 F
b11111 4
b110001 7
b11 L
b101 K
b101 J
12
#530000
02
#535000
b1001 F
b1000 "
b1000 H
0&
b100000 4
b110010 7
b11 L
b101 K
b101 J
12
#540000
02
#545000
b1001 "
b1001 H
b1010 F
b110011 7
b11 L
b101 K
b101 J
12
#550000
02
#555000
b1011 F
b1010 "
b1010 H
1$
b110100 7
b11 L
b101 K
b101 J
12
#560000
02
#565000
b1011 "
b1011 H
b1100 F
b110101 7
b11 L
b101 K
b101 J
12
#570000
02
#575000
b1101 F
b1100 "
b1100 H
0$
b110110 7
b11 L
b101 K
b101 J
12
#580000
02
#585000
b1101 "
b1101 H
b100 G
b0 F
b110111 7
b11 L
b101 K
b101 J
12
#590000
02
#595000
b1 F
b100 !
b100 I
b0 "
b0 H
b111000 7
b100 L
b101 K
b101 J
12
#600000
02
#605000
b1 "
b1 H
b10 F
b101 6
b111001 7
b100 L
b101 K
b101 J
12
#610000
02
#615000
b11 F
b10 "
b10 H
b111010 7
b100 L
b101 K
b101 J
12
#620000
02
#625000
b11 "
b11 H
b100 F
b111011 7
b100 L
b101 K
b101 J
12
#630000
02
#635000
b101 F
b100 "
b100 H
b111100 7
b101 K
b101 J
12
#640000
02
#645000
b101 "
b101 H
b110 F
b111101 7
b100 L
b101 K
b101 J
12
#650000
02
#655000
b111 F
b110 "
b110 H
b111110 7
b100 L
b101 K
b101 J
12
#660000
02
#665000
b111 "
b111 H
b1000 F
b111111 7
b100 L
b101 K
b101 J
12
#670000
02
#675000
b1001 F
b1000 "
b1000 H
b1000000 7
b100 L
b101 K
b101 J
12
#680000
02
#685000
b1001 "
b1001 H
b1010 F
b1000001 7
b100 L
b101 K
b101 J
12
#690000
02
#695000
b1011 F
b1010 "
b1010 H
1$
b1000010 7
b100 L
b101 K
b101 J
12
#700000
02
#705000
b1011 "
b1011 H
b1100 F
b1000011 7
b100 L
b101 K
b101 J
12
#710000
02
#715000
b1101 F
b1100 "
b1100 H
0$
b1000100 7
b100 L
b101 K
b101 J
12
#720000
02
#725000
b1101 "
b1101 H
b101 G
b0 F
b1000101 7
b100 L
b101 K
b101 J
12
#730000
02
#735000
b1 F
b101 !
b101 I
b0 "
b0 H
1#
b1000110 7
b101 L
b101 K
b101 J
12
#740000
02
#745000
b1 "
b1 H
b10 F
b110 6
b1000111 7
b101 L
b101 K
b101 J
12
#750000
02
#755000
b11 F
b10 "
b10 H
b1001000 7
b101 L
b101 K
b101 J
12
#760000
02
#765000
b11 "
b11 H
b100 F
b1001001 7
b101 L
b101 K
b101 J
12
#770000
02
#775000
b101 F
b100 "
b100 H
b1001010 7
b101 L
b101 K
b101 J
12
#780000
02
#785000
b101 "
b101 H
b110 F
b1001011 7
b101 K
b101 J
12
#790000
02
#795000
b111 F
b110 "
b110 H
b1001100 7
b101 L
b101 K
b101 J
12
#800000
02
#805000
b111 "
b111 H
b1000 F
b1001101 7
b101 L
b101 K
b101 J
12
#810000
02
#815000
b1001 F
b1000 "
b1000 H
b1001110 7
b101 L
b101 K
b101 J
12
#820000
02
#825000
b1001 "
b1001 H
b1010 F
b1001111 7
b101 L
b101 K
b101 J
12
#830000
02
#835000
b1011 F
b1010 "
b1010 H
1$
b1010000 7
b101 L
b101 K
b101 J
12
#840000
02
#845000
b1011 "
b1011 H
b1100 F
b1010001 7
b101 L
b101 K
b101 J
12
#850000
02
#855000
b1101 F
b1100 "
b1100 H
0$
b1010010 7
b101 L
b101 K
b101 J
12
#860000
02
#865000
b1101 "
b1101 H
b110 G
b0 F
b1010011 7
b101 L
b101 K
b101 J
12
#870000
02
#875000
b1 F
b110 !
b110 I
b0 "
b0 H
0#
b1010100 7
b110 L
b101 K
b101 J
12
#880000
02
#885000
b1 "
b1 H
b10 F
b111 6
b1010101 7
b110 L
b101 K
b101 J
12
#890000
02
#895000
b11 F
b10 "
b10 H
b1010110 7
b110 L
b101 K
b101 J
12
#900000
02
#905000
b11 "
b11 H
b100 F
b1010111 7
b110 L
b101 K
b101 J
12
#910000
02
#915000
b101 F
b100 "
b100 H
b1011000 7
b110 L
b101 K
b101 J
12
#920000
02
#925000
b101 "
b101 H
b110 F
b1011001 7
b110 L
b101 K
b101 J
12
#930000
02
#935000
b111 F
b110 "
b110 H
b1011010 7
b101 K
b101 J
12
#940000
02
#945000
b111 "
b111 H
b1000 F
b1011011 7
b110 L
b101 K
b101 J
12
#950000
02
#955000
b1001 F
b1000 "
b1000 H
b1011100 7
b110 L
b101 K
b101 J
12
#960000
02
#965000
b1001 "
b1001 H
b1010 F
b1011101 7
b110 L
b101 K
b101 J
12
#970000
02
#975000
b1011 F
b1010 "
b1010 H
1$
b1011110 7
b110 L
b101 K
b101 J
12
#980000
02
#985000
b1011 "
b1011 H
b1100 F
b1011111 7
b110 L
b101 K
b101 J
12
#990000
02
#995000
1%
b1101 F
b1100 "
b1100 H
0$
b1100000 7
b110 L
b101 K
b101 J
12
#1000000
02
#1005000
0%
b1101 "
b1101 H
b0 G
b0 F
b0 6
b0 4
b1 5
b0 7
b110 L
b101 K
b101 J
12
#1010000
02
#1015000
b1 F
b0 !
b0 I
b0 "
b0 H
1&
b1 7
b0 L
b101 K
b101 J
12
#1020000
02
#1025000
b1 "
b1 H
b10 F
b1 4
b1 6
b10 7
b0 L
b101 K
b101 J
12
#1030000
02
#1035000
b11 F
b10 "
b10 H
b10 4
b11 7
b0 L
b101 K
b101 J
12
#1040000
02
#1045000
b11 "
b11 H
b100 F
b11 4
b100 7
b0 L
b101 K
b101 J
12
#1050000
02
#1055000
b101 F
b100 "
b100 H
b100 4
b101 7
b0 L
b101 K
b101 J
12
#1060000
02
#1065000
b101 "
b101 H
b110 F
b101 4
b110 7
b0 L
b101 K
b101 J
12
#1070000
02
#1075000
b111 F
b110 "
b110 H
b110 4
b111 7
b0 L
b101 K
b101 J
12
#1080000
02
#1085000
b111 "
b111 H
b1000 F
b111 4
b1000 7
b0 L
b101 K
b101 J
12
#1090000
02
#1095000
b1001 F
b1000 "
b1000 H
0&
b1000 4
b1001 7
b0 L
b101 K
b101 J
12
#1100000
02
#1105000
b1001 "
b1001 H
b1010 F
b1010 7
b0 L
b101 K
b101 J
12
#1110000
02
#1115000
b1011 F
b1010 "
b1010 H
1$
b1011 7
b0 L
b101 K
b101 J
12
#1120000
02
#1125000
b1011 "
b1011 H
b1100 F
b1100 7
b0 L
b101 K
b101 J
12
#1130000
02
#1135000
b1101 F
b1100 "
b1100 H
0$
b1101 7
b0 L
b101 K
b101 J
12
#1140000
02
#1145000
b1101 "
b1101 H
b1 G
b0 F
b1110 7
b0 L
b101 K
b101 J
12
#1150000
02
#1155000
b1 F
b1 !
b1 I
b0 "
b0 H
1&
b1111 7
b1 L
b101 K
b101 J
12
#1160000
02
#1165000
b1 "
b1 H
b10 F
b1001 4
b10 6
b10000 7
b101 K
b101 J
12
#1170000
02
#1175000
b11 F
b10 "
b10 H
b1010 4
b10001 7
b1 L
b101 K
b101 J
12
#1180000
02
#1185000
b11 "
b11 H
b100 F
b1011 4
b10010 7
b1 L
b101 K
b101 J
12
#1190000
02
#1195000
b101 F
b100 "
b100 H
b1100 4
b10011 7
b1 L
b101 K
b101 J
12
#1200000
02
#1205000
b101 "
b101 H
b110 F
b1101 4
b10100 7
b1 L
b101 K
b101 J
12
#1210000
02
#1215000
b111 F
b110 "
b110 H
b1110 4
b10101 7
b1 L
b101 K
b101 J
12
#1220000
02
#1225000
b111 "
b111 H
b1000 F
b1111 4
b10110 7
b1 L
b101 K
b101 J
12
#1230000
02
#1235000
b1001 F
b1000 "
b1000 H
0&
b10000 4
b10111 7
b1 L
b101 K
b101 J
12
#1240000
02
#1245000
b1001 "
b1001 H
b1010 F
b11000 7
b1 L
b101 K
b101 J
12
#1250000
02
#1255000
b1011 F
b1010 "
b1010 H
1$
b11001 7
b1 L
b101 K
b101 J
12
#1260000
02
#1265000
b1011 "
b1011 H
b1100 F
b11010 7
b1 L
b101 K
b101 J
12
#1270000
02
#1275000
b1101 F
b1100 "
b1100 H
0$
b11011 7
b1 L
b101 K
b101 J
12
#1280000
02
#1285000
b1101 "
b1101 H
b10 G
b0 F
b11100 7
b1 L
b101 K
b101 J
12
#1290000
02
#1295000
b1 F
b10 !
b10 I
b0 "
b0 H
1&
b11101 7
b10 L
b101 K
b101 J
12
#1300000
02
#1305000
b1 "
b1 H
b10 F
b10001 4
b11 6
b11110 7
b10 L
b101 K
b101 J
12
#1310000
02
#1315000
b11 F
b10 "
b10 H
b10010 4
b11111 7
b101 K
b101 J
12
#1320000
02
#1325000
b11 "
b11 H
b100 F
b10011 4
b100000 7
b10 L
b101 K
b101 J
12
#1330000
02
#1335000
b101 F
b100 "
b100 H
b10100 4
b100001 7
b10 L
b101 K
b101 J
12
#1340000
02
#1345000
b101 "
b101 H
b110 F
b10101 4
b100010 7
b10 L
b101 K
b101 J
12
#1350000
02
#1355000
b111 F
b110 "
b110 H
b10110 4
b100011 7
b10 L
b101 K
b101 J
12
#1360000
02
#1365000
b111 "
b111 H
b1000 F
b10111 4
b100100 7
b10 L
b101 K
b101 J
12
#1370000
02
#1375000
b1001 F
b1000 "
b1000 H
0&
b11000 4
b100101 7
b10 L
b101 K
b101 J
12
#1380000
02
#1385000
b1001 "
b1001 H
b1010 F
b100110 7
b10 L
b101 K
b101 J
12
#1390000
02
#1395000
b1011 F
b1010 "
b1010 H
1$
b100111 7
b10 L
b101 K
b101 J
12
#1400000
02
#1405000
b1011 "
b1011 H
b1100 F
b101000 7
b10 L
b101 K
b101 J
12
#1410000
02
#1415000
b1101 F
b1100 "
b1100 H
0$
b101001 7
b10 L
b101 K
b101 J
12
#1420000
02
#1425000
b1101 "
b1101 H
b11 G
b0 F
b101010 7
b10 L
b101 K
b101 J
12
#1430000
02
#1435000
b1 F
b11 !
b11 I
b0 "
b0 H
1&
b101011 7
b11 L
b101 K
b101 J
12
#1440000
02
#1445000
b1 "
b1 H
b10 F
b11001 4
b100 6
b101100 7
b11 L
b101 K
b101 J
12
#1450000
02
#1455000
b11 F
b10 "
b10 H
b11010 4
b101101 7
b11 L
b101 K
b101 J
12
#1460000
02
#1465000
b11 "
b11 H
b100 F
b11011 4
b101110 7
b101 K
b101 J
12
#1470000
02
#1475000
b101 F
b100 "
b100 H
b11100 4
b101111 7
b11 L
b101 K
b101 J
12
#1480000
02
#1485000
b101 "
b101 H
b110 F
b11101 4
b110000 7
b11 L
b101 K
b101 J
12
#1490000
02
#1495000
b111 F
b110 "
b110 H
b11110 4
b110001 7
b11 L
b101 K
b101 J
12
#1500000
02
#1505000
b111 "
b111 H
b1000 F
b11111 4
b110010 7
b11 L
b101 K
b101 J
12
#1510000
02
#1515000
b1001 F
b1000 "
b1000 H
0&
b100000 4
b110011 7
b11 L
b101 K
b101 J
12
#1520000
02
#1525000
b1001 "
b1001 H
b1010 F
b110100 7
b11 L
b101 K
b101 J
12
#1530000
02
#1535000
b1011 F
b1010 "
b1010 H
1$
b110101 7
b11 L
b101 K
b101 J
12
#1540000
02
#1545000
b1011 "
b1011 H
b1100 F
b110110 7
b11 L
b101 K
b101 J
12
#1550000
02
#1555000
b1101 F
b1100 "
b1100 H
0$
b110111 7
b11 L
b101 K
b101 J
12
#1560000
02
#1565000
b1101 "
b1101 H
b100 G
b0 F
b111000 7
b11 L
b101 K
b101 J
12
#1570000
02
#1575000
b1 F
b100 !
b100 I
b0 "
b0 H
b111001 7
b100 L
b101 K
b101 J
12
#1580000
02
#1585000
b1 "
b1 H
b10 F
b101 6
b111010 7
b100 L
b101 K
b101 J
12
#1590000
02
#1595000
b11 F
b10 "
b10 H
b111011 7
b100 L
b101 K
b101 J
12
#1600000
02
#1605000
b11 "
b11 H
b100 F
b111100 7
b100 L
b101 K
b101 J
12
#1610000
02
#1615000
b101 F
b100 "
b100 H
b111101 7
b101 K
b101 J
12
#1620000
02
#1625000
b101 "
b101 H
b110 F
b111110 7
b100 L
b101 K
b101 J
12
#1630000
02
#1635000
b111 F
b110 "
b110 H
b111111 7
b100 L
b101 K
b101 J
12
#1640000
02
#1645000
b111 "
b111 H
b1000 F
b1000000 7
b100 L
b101 K
b101 J
12
#1650000
02
#1655000
b1001 F
b1000 "
b1000 H
b1000001 7
b100 L
b101 K
b101 J
12
#1660000
02
#1665000
b1001 "
b1001 H
b1010 F
b1000010 7
b100 L
b101 K
b101 J
12
#1670000
02
#1675000
b1011 F
b1010 "
b1010 H
1$
b1000011 7
b100 L
b101 K
b101 J
12
#1680000
02
#1685000
b1011 "
b1011 H
b1100 F
b1000100 7
b100 L
b101 K
b101 J
12
#1690000
02
#1695000
b1101 F
b1100 "
b1100 H
0$
b1000101 7
b100 L
b101 K
b101 J
12
#1700000
02
#1705000
b1101 "
b1101 H
b101 G
b0 F
b1000110 7
b100 L
b101 K
b101 J
12
#1710000
02
#1715000
b1 F
b101 !
b101 I
b0 "
b0 H
1#
b1000111 7
b101 L
b101 K
b101 J
12
#1720000
02
#1725000
b1 "
b1 H
b10 F
b110 6
b1001000 7
b101 L
b101 K
b101 J
12
#1730000
02
#1735000
b11 F
b10 "
b10 H
b1001001 7
b101 L
b101 K
b101 J
12
#1740000
02
#1745000
b11 "
b11 H
b100 F
b1001010 7
b101 L
b101 K
b101 J
12
#1750000
02
#1755000
b101 F
b100 "
b100 H
b1001011 7
b101 L
b101 K
b101 J
12
#1760000
02
#1765000
b101 "
b101 H
b110 F
b1001100 7
b101 K
b101 J
12
#1770000
02
#1775000
b111 F
b110 "
b110 H
b1001101 7
b101 L
b101 K
b101 J
12
#1780000
02
#1785000
b111 "
b111 H
b1000 F
b1001110 7
b101 L
b101 K
b101 J
12
#1790000
02
#1795000
b1001 F
b1000 "
b1000 H
b1001111 7
b101 L
b101 K
b101 J
12
#1800000
02
#1805000
b1001 "
b1001 H
b1010 F
b1010000 7
b101 L
b101 K
b101 J
12
#1810000
02
#1815000
b1011 F
b1010 "
b1010 H
1$
b1010001 7
b101 L
b101 K
b101 J
12
#1820000
02
#1825000
b1011 "
b1011 H
b1100 F
b1010010 7
b101 L
b101 K
b101 J
12
#1830000
02
#1835000
b1101 F
b1100 "
b1100 H
0$
b1010011 7
b101 L
b101 K
b101 J
12
#1840000
02
#1845000
b1101 "
b1101 H
b110 G
b0 F
b1010100 7
b101 L
b101 K
b101 J
12
#1850000
02
#1855000
b1 F
b110 !
b110 I
b0 "
b0 H
0#
b1010101 7
b110 L
b101 K
b101 J
12
#1860000
02
#1865000
b1 "
b1 H
b10 F
b111 6
b1010110 7
b110 L
b101 K
b101 J
12
#1870000
02
#1875000
b11 F
b10 "
b10 H
b1010111 7
b110 L
b101 K
b101 J
12
#1880000
02
#1885000
b11 "
b11 H
b100 F
b1011000 7
b110 L
b101 K
b101 J
12
#1890000
02
#1895000
b101 F
b100 "
b100 H
b1011001 7
b110 L
b101 K
b101 J
12
#1900000
02
#1905000
b101 "
b101 H
b110 F
b1011010 7
b110 L
b101 K
b101 J
12
#1910000
02
#1915000
b111 F
b110 "
b110 H
b1011011 7
b101 K
b101 J
12
#1920000
02
#1925000
b111 "
b111 H
b1000 F
b1011100 7
b110 L
b101 K
b101 J
12
#1930000
02
#1935000
b1001 F
b1000 "
b1000 H
b1011101 7
b110 L
b101 K
b101 J
12
#1940000
02
#1945000
b1001 "
b1001 H
b1010 F
b1011110 7
b110 L
b101 K
b101 J
12
#1950000
02
#1955000
b1011 F
b1010 "
b1010 H
1$
b1011111 7
b110 L
b101 K
b101 J
12
